Workbook

Sheet September
A1: Kids | Q1: Salario Mensual | R1: Salario Quincenal
A3: Nombre | B3: Mensual | C3: Quincenal | D3: Es Anual | E3: Costo Anual | F3: Costo Mensual | G3: Comentarios | H3: Cuenta Cargo | I3: Cuenta deposito
A4: Colegiatura Lena | B4: =CEILING(F4,100) -> 17500 | C4: =CEILING(B4/2, 10) -> 8750 | D4: =IF(E4>0, true) -> FALSE | F4: 17500 | H4: HSBC World elite | I4: Uala
A5: Colegiatura Leander | B5: =CEILING(F5,100) -> 12500 | C5: =CEILING(B5/2, 10) -> 6250 | D5: =IF(E5>0, true) -> FALSE | F5: 12500 | H5: Uala | I5: Uala
A6: Clases de aleman | B6: =CEILING(F6,100) -> 4400 | C6: =CEILING(B6/2, 10) -> 2200 | D6: =IF(E6>0, true) -> FALSE | F6: =550*8 -> 4400 | G6: 8 clases al mes (2 clases semanales) | H6: HSBC World elite | I6: HSBC
A7: Gimnasia | B7: =CEILING(F7,100) -> 2500 | C7: =CEILING(B7/2, 10) -> 1250 | D7: =IF(E7>0, true) -> FALSE | F7: 2500 | H7: Uala | I7: Uala
A8: Inscripcion Lena | B8: =CEILING(F8,100) -> 1600 | C8: =CEILING(B8/2, 10) -> 800 | D8: =IF(E8>0, true) -> TRUE | E8: 19000 | F8: =E8/12 -> 1583.3333 | G8: Al menos 50% de la siguiente inscripcion | H8: HSBC World elite | I8: Stori Inversion +
A9: Natacion Lena | B9: =CEILING(F9,100) -> 1300 | C9: =CEILING(B9/2, 10) -> 650 | D9: =IF(E9>0, true) -> FALSE | F9: 1270 | H9: HSBC World elite | I9: Uala
A10: Natacion Leander | B10: =CEILING(F10,100) -> 1300 | C10: =CEILING(B10/2, 10) -> 650 | D10: =IF(E10>0, true) -> FALSE | F10: 1270 | H10: HSBC World elite | I10: Uala
A11: Little Kickers | B11: =CEILING(F11,100) -> 1300 | C11: =CEILING(B11/2, 10) -> 650 | D11: =IF(E11>0, true) -> FALSE | F11: 1250 | H11: HSBC World elite | I11: Uala
A12: Inscripcion Leander | B12: =CEILING(F12,100) -> 1000 | C12: =CEILING(B12/2, 10) -> 500 | D12: =IF(E12>0, true) -> TRUE | E12: 12000 | F12: =E12/12 -> 1000 | H12: Uala | I12: Stori Inversion + | M12: =E8+E14+E22+E23+E25+E27+E28+E53+E54+E56+E72 -> 49839
A15: Total | B15: =SUM(B3:B14) -> 43400 | C15: =SUM(C3:C14) -> 21700 | F15: =SUM(F3:F14) -> 43273.333
A17: Suscripciones | M17: =62517+1700 -> 64217
A19: Nombre | B19: Mensual | C19: Quincenal | D19: Es Anual | H19: Cuenta Cargo | I19: Cuenta Deposito
A20: Sports World | B20: =CEILING(F20,100) -> 3900 | C20: =CEILING(B20/2, 10) -> 1950 | D20: =IF(E20>0, true) -> FALSE | F20: 3850 | H20: HSBC World elite | I20: Nu Cajita Gastos
A21: Netflix | B21: =CEILING(F21,100) -> 400 | C21: =CEILING(B21/2, 10) -> 200 | D21: =IF(E21>0, true) -> FALSE | F21: 350 | H21: 2Now Gastos | I21: Nu Cajita Gastos
A22: NFL game pass | B22: =CEILING(F22,100) -> 300 | C22: =CEILING(B22/2, 10) -> 150 | D22: =IF(E22>0, true) -> TRUE | E22: 3300 | F22: =E22/12 -> 275 | H22: HSBC World elite | I22: Stori Inversion +
A23: Disney | B23: =CEILING(F23,100) -> 200 | C23: =CEILING(B23/2, 10) -> 100 | D23: =IF(E23>0, true) -> TRUE | E23: 2400 | F23: =E23/12 -> 200 | H23: 2Now Gastos | I23: Nu Cajita Gastos
A24: Max | B24: =CEILING(F24,100) -> 200 | C24: =CEILING(B24/2, 10) -> 100 | D24: =IF(E24>0, true) -> FALSE | F24: 199 | H24: 2Now Gastos | I24: Nu Cajita Gastos
A25: Spotify | B25: =CEILING(F25,100) -> 200 | C25: =CEILING(B25/2, 10) -> 100 | D25: =IF(E25>0, true) -> TRUE | E25: 1990 | F25: =E25/12 -> 165.83333 | H25: HSBC World elite | I25: Stori Inversion +
A26: Digital Ocean | B26: =CEILING(F26,100) -> 200 | C26: =CEILING(B26/2, 10) -> 100 | D26: =IF(E26>0, true) -> FALSE | F26: 130 | H26: HSBC World elite | I26: Nu Cajita Gastos
A27: Prime | B27: =CEILING(F27,100) -> 100 | C27: =CEILING(B27/2, 10) -> 50 | D27: =IF(E27>0, true) -> TRUE | E27: 899 | F27: =E27/12 -> 74.916667 | H27: HSBC World elite | I27: Stori Inversion +
A28: Uber one | B28: =CEILING(F28,100) -> 100 | C28: =CEILING(B28/2, 10) -> 50 | D28: =IF(E28>0, true) -> TRUE | E28: 750 | F28: =E28/12 -> 62.5 | H28: HSBC World elite | I28: Stori Inversion +
A29: Frontend masters | B29: =CEILING(F29,100) -> 0 | C29: =CEILING(B29/2, 10) -> 0 | D29: =IF(E29>0, true) -> FALSE | H29: HSBC World elite | I29: Nu Cajita Gastos
A31: Total | B31: =SUM(B20:B29) -> 5600 | C31: =SUM(C20:C29) -> 2800 | F31: =SUM(F20:F29) -> 5307.25
A33: Telecomunicaciones
A34: Nombre | B34: Mensual | C34: Quincenal | D34: Es Anual | H34: Cuenta Cargo | I34: Cuenta Deposito
A35: Totalplay (Internet + TV) | B35: =CEILING(F35,100) -> 1200 | C35: =CEILING(B35/2, 10) -> 600 | D35: =IF(E35>0, true) -> FALSE | F35: 1200 | H35: 2Now Hogar | I35: Nu Cajita Hogar
A36: Movistar Dalia | B36: =CEILING(F36,100) -> 500 | C36: =CEILING(B36/2, 10) -> 250 | D36: =IF(E36>0, true) -> FALSE | F36: 500 | H36: 2Now Gastos | I36: Nu Cajita Gastos
A37: Movistar Alfredo | B37: =CEILING(F37,100) -> 500 | C37: =CEILING(B37/2, 10) -> 250 | D37: =IF(E37>0, true) -> FALSE | F37: 500 | H37: 2Now Gastos | I37: Nu Cajita Gastos
A39: Total | B39: =SUM(B35:B38) -> 2200 | C39: =SUM(C35:C38) -> 1100 | F39: =SUM(F35:F38) -> 2200
A41: Ahorro
A42: Nombre | B42: Mensual | C42: Quincenal | D42: Es Anual | H42: Cuenta Cargo | I42: Cuenta Deposito
A43: Trading | B43: =CEILING(F43,100) -> 800 | C43: =CEILING(B43/2, 10) -> 400 | D43: =IF(E43>0, true) -> FALSE | F43: 800 | H43: HSBC | I43: GBM Trading
A44: Dolares | B44: =CEILING(F44,100) -> 0 | C44: =CEILING(B44/2, 10) -> 0 | D44: =IF(E44>0, true) -> FALSE | H44: HSBC | I44: GBM Dolares
A45: Largo plazo | B45: =CEILING(F45,100) -> 0 | C45: =CEILING(B45/2, 10) -> 0 | D45: =IF(E45>0, true) -> FALSE | H45: Stori Inversion + | I45: Stori Inversion +
A47: Total | B47: =SUM(B43:B45) -> 800 | C47: =SUM(C43:C45) -> 400 | F47: =SUM(F43:F45) -> 800
A49: Auto
A50: Nombre | B50: Mensual | C50: Quincenal | D50: Es Anual | H50: Cuenta Cargo | I50: Cuenta Deposito
A51: Nuevo Auto | B51: =CEILING(F51,100) -> 11000 | C51: =CEILING(B51/2, 10) -> 5500 | D51: =IF(E51>0, true) -> FALSE | F51: 11000 | H51: HSBC | I51: Nu Cajita Auto
A52: Gasolina | B52: =CEILING(F52,100) -> 3600 | C52: =CEILING(B52/2, 10) -> 1800 | D52: =IF(E52>0, true) -> FALSE | F52: =1200*3 -> 3600 | H52: 2Now Gastos | I52: Nu Cajita Auto
A53: Seguro | B53: =CEILING(F53,100) -> 800 | C53: =CEILING(B53/2, 10) -> 400 | D53: =IF(E53>0, true) -> TRUE | E53: 8500 | F53: =E53/12 -> 708.33333 | H53: 2Now Gastos | I53: Nu Cajita Auto | X53: =#REF!+#REF!+Deuda!E4+#REF!+#REF!+#REF! -> #REF!
A54: Matenimiento | B54: =CEILING(F54,100) -> 800 | C54: =CEILING(B54/2, 10) -> 400 | D54: =IF(E54>0, true) -> TRUE | E54: 9000 | F54: =E54/12 -> 750 | H54: 2Now Gastos | I54: Nu Cajita Auto
A55: Lavado | B55: =CEILING(F55,100) -> 500 | C55: =CEILING(B55/2, 10) -> 250 | D55: =IF(E55>0, true) -> FALSE | F55: =250*2 -> 500 | G55: 2 lavados al mes | H55: 2Now Gastos | I55: Nu Cajita Auto
A56: Tenencia | B56: =CEILING(F56,100) -> 300 | C56: =CEILING(B56/2, 10) -> 150 | D56: =IF(E56>0, true) -> TRUE | E56: 3000 | F56: =E56/12 -> 250 | H56: 2Now Gastos | I56: Nu Cajita Auto
A57: Verificacion | B57: =CEILING(F57,100) -> 200 | C57: =CEILING(B57/2, 10) -> 100 | D57: =IF(E57>0, true) -> TRUE | E57: =738*2 -> 1476 | F57: =E57/12 -> 123 | H57: 2Now Gastos | I57: Nu Cajita Auto
A59: Total | B59: =SUM(B51:B58) -> 17200 | C59: =SUM(C51:C58) -> 8600 | F59: =SUM(F51:F57) -> 16931.333
A61: Zuhause
A62: Nombre | B62: Mensual | C62: Quincenal | D62: Es Anual | H62: Cuenta Cargo | I62: Cuenta Deposito
A63: Renta | B63: =CEILING(F63,100) -> 37500 | C63: =CEILING(B63/2, 10) -> 18750 | D63: =IF(E63>0, true) -> FALSE | F63: 37500 | H63: HSBC | I63: HSBC Flexible
A64: Supermercado y comida | B64: =CEILING(F64,100) -> 18000 | C64: =CEILING(B64/2, 10) -> 9000 | D64: =IF(E64>0, true) -> FALSE | F64: 18000 | H64: 2Now Hogar | I64: Nu Cajita Hogar
A65: Limpieza Alicia | B65: =CEILING(F65,100) -> 3600 | C65: =CEILING(B65/2, 10) -> 1800 | D65: =IF(E65>0, true) -> FALSE | F65: =450*8 -> 3600 | G65: 450, contando 8 limpiezas al mes | H65: HSBC | I65: HSBC
A66: Limpieza Sra Dalia | B66: =CEILING(F66,100) -> 2000 | C66: =CEILING(B66/2, 10) -> 1000 | D66: =IF(E66>0, true) -> FALSE | F66: =500*4 -> 2000 | G66: 4 jueves por mes | H66: HSBC | I66: HSBC
A67: Cuota Admin. Sta Anita | B67: =CEILING(F67,100) -> 1800 | C67: =CEILING(B67/2, 10) -> 900 | D67: =IF(E67>0, true) -> FALSE | F67: 1800 | H67: HSBC | I67: HSBC Flexible
A68: Gas | B68: =CEILING(F68,100) -> 1000 | C68: =CEILING(B68/2, 10) -> 500 | D68: =IF(E68>0, true) -> FALSE | F68: 1000 | G68: Recargando 2000 cada 2 meses | H68: 2Now Hogar | I68: Nu Cajita Hogar
A69: Electricidad | B69: =CEILING(F69,100) -> 800 | C69: =CEILING(B69/2, 10) -> 400 | D69: =IF(E69>0, true) -> FALSE | F69: =1500/2 -> 750 | G69: Asumiendo un gasto de 1500 al bimestre | H69: 2Now Hogar | I69: Nu Cajita Hogar
A70: Agua | B70: =CEILING(F70,100) -> 400 | C70: =CEILING(B70/2, 10) -> 200 | D70: =IF(E70>0, true) -> FALSE | F70: =(500+120)/2 -> 310 | G70: 450 Bartolache + 120 Santa Anita | H70: 2Now Hogar | I70: Nu Cajita Hogar
A71: Basura (Sr. Polo) | B71: =CEILING(F71,100) -> 300 | C71: =CEILING(B71/2, 10) -> 150 | D71: =IF(E71>0, true) -> FALSE | F71: =70*4 -> 280 | H71: HSBC | I71: HSBC
A72: Predial Sta Anita | B72: =CEILING(F72,100) -> 100 | C72: =CEILING(B72/2, 10) -> 50 | D72: =IF(E72>0, true) -> TRUE | E72: 1000 | F72: =E72/12 -> 83.333333 | H72: 2Now Hogar | I72: Stori Inversion +
A73: ISR Renta Departamento | B73: =CEILING(F73,100) -> 200 | C73: =CEILING(B73/2, 10) -> 100 | D73: =IF(E73>0, true) -> FALSE | F73: 110 | H73: HSBC | I73: HSBC
A74: Hipoteca | B74: =CEILING(F74,100) -> 0 | C74: =CEILING(B74/2, 10) -> 0 | D74: =IF(E74>0, true) -> FALSE | H74: HSBC | I74: HSBC
A76: Total | B76: =SUM(B63:B75) -> 65700 | C76: =SUM(C63:C75) -> 32850 | F76: =SUM(F63:F75) -> 65433.333
A78: Miscelaneos
A79: Nombre | B79: Mensual | C79: Quincenal | D79: Es Anual | H79: Cuenta Cargo | I79: Cuenta Deposito
A80: Libre | B80: =CEILING(F80,100) -> 5800 | C80: =CEILING(B80/2, 10) -> 2900 | D80: FALSE | F80: 5750 | H80: 2Now Gastos | I80: Nu Cajita Gastos
A81: Efectivo | B81: =CEILING(F81,100) -> 3000 | C81: =CEILING(B81/2, 10) -> 1500 | D81: FALSE | F81: 3000 | H81: HSBC | I81: HSBC
A82: Dalia mensualidad | B82: =CEILING(F82,100) -> 2300 | C82: =CEILING(B82/2, 10) -> 1150 | D82: FALSE | F82: 2300 | H82: Nu Dalia Debito | I82: Nu Dalia Debito
A84: Total | B84: =SUM(B80:B83) -> 11100 | C84: =SUM(C80:C83) -> 5550 | F84: =SUM(F80:F83) -> 11050

Sheet September of Totales y Transfer
A1: Column 1 | B1: CLABE | C1: Referencia en deposito | D1: Total Mensual | E1: Total quincenal | F1: Programada
A2: HSBC Flexible | B2: {=INDEX(Table3[CLABE], MATCH(A2, Table3[Nombre cuenta], 0))} -> 021180065930525793 | C2: {=INDEX(Table3[Codigo Referencia], MATCH(A2, Table3[Nombre cuenta], 0))} -> 0000011 | D2: =SUMIF(September!$I$3:$I$88, A2, September!$B$3:$B$88) -> 39300 | E2: =SUMIF(September!$I$3:$I$88, A2, September!$C$3:$C$88) -> 19650 | F2: TRUE | H2: x
A3: Uala | B3: {=INDEX(Table3[CLABE], MATCH(A3, Table3[Nombre cuenta], 0))} -> 138580000023894928 | C3: {=INDEX(Table3[Codigo Referencia], MATCH(A3, Table3[Nombre cuenta], 0))} -> 0000014 | D3: =SUMIF(September!$I$3:$I$88, A3, September!$B$3:$B$88) -> 36400 | E3: =SUMIF(September!$I$3:$I$88, A3, September!$C$3:$C$88) -> 18200 | F3: TRUE | H3: x
A4: Nu Cajita Hogar | B4: {=INDEX(Table3[CLABE], MATCH(A4, Table3[Nombre cuenta], 0))} -> 638180000177404193 | C4: {=INDEX(Table3[Codigo Referencia], MATCH(A4, Table3[Nombre cuenta], 0))} -> 0000016 | D4: =SUMIF(September!$I$3:$I$88, A4, September!$B$3:$B$88) -> 21400 | E4: =SUMIF(September!$I$3:$I$88, A4, September!$C$3:$C$88) -> 10700 | F4: TRUE | H4: x
A5: Nu Cajita Auto | B5: {=INDEX(Table3[CLABE], MATCH(A5, Table3[Nombre cuenta], 0))} -> 638180000177404193 | C5: {=INDEX(Table3[Codigo Referencia], MATCH(A5, Table3[Nombre cuenta], 0))} -> 0000012 | D5: =SUMIF(September!$I$3:$I$88, A5, September!$B$3:$B$88) -> 17200 | E5: =SUMIF(September!$I$3:$I$88, A5, September!$C$3:$C$88) -> 8600 | F5: TRUE | H5: x
A6: HSBC | B6: {=INDEX(Table3[CLABE], MATCH(A6, Table3[Nombre cuenta], 0))} -> 021180040690613986 | C6: {=INDEX(Table3[Codigo Referencia], MATCH(A6, Table3[Nombre cuenta], 0))} -> 0000001 | D6: =SUMIF(September!$I$3:$I$88, A6, September!$B$3:$B$88) -> 13500 | E6: =SUMIF(September!$I$3:$I$88, A6, September!$C$3:$C$88) -> 6750 | F6: FALSE
A7: Nu Cajita Gastos | B7: {=INDEX(Table3[CLABE], MATCH(A7, Table3[Nombre cuenta], 0))} -> 638180000177404193 | C7: {=INDEX(Table3[Codigo Referencia], MATCH(A7, Table3[Nombre cuenta], 0))} -> 0000013 | D7: =SUMIF(September!$I$3:$I$88, A7, September!$B$3:$B$88) -> 11700 | E7: =SUMIF(September!$I$3:$I$88, A7, September!$C$3:$C$88) -> 5850 | F7: TRUE | H7: x
A8: Stori Inversion + | B8: {=INDEX(Table3[CLABE], MATCH(A8, Table3[Nombre cuenta], 0))} -> 646180402300057567 | C8: {=INDEX(Table3[Codigo Referencia], MATCH(A8, Table3[Nombre cuenta], 0))} -> 0000015 | D8: =SUMIF(September!$I$3:$I$88, A8, September!$B$3:$B$88) -> 3400 | E8: =SUMIF(September!$I$3:$I$88, A8, September!$C$3:$C$88) -> 1700 | F8: TRUE | H8: x
A9: Nu Dalia Debito | B9: {=INDEX(Table3[CLABE], MATCH(A9, Table3[Nombre cuenta], 0))} -> 638180010151893079 | C9: {=INDEX(Table3[Codigo Referencia], MATCH(A9, Table3[Nombre cuenta], 0))} -> 0000004 | D9: =SUMIF(September!$I$3:$I$88, A9, September!$B$3:$B$88) -> 2300 | E9: =SUMIF(September!$I$3:$I$88, A9, September!$C$3:$C$88) -> 1150 | F9: TRUE | H9: x
A10: GBM Trading | B10: {=INDEX(Table3[CLABE], MATCH(A10, Table3[Nombre cuenta], 0))} -> 601180400038253515 | C10: {=INDEX(Table3[Codigo Referencia], MATCH(A10, Table3[Nombre cuenta], 0))} -> 0000104 | D10: =SUMIF(September!$I$3:$I$88, A10, September!$B$3:$B$88) -> 800 | E10: =SUMIF(September!$I$3:$I$88, A10, September!$C$3:$C$88) -> 400 | F10: TRUE
A11: GBM Dolares | B11: {=INDEX(Table3[CLABE], MATCH(A11, Table3[Nombre cuenta], 0))} -> 601180400049499232 | C11: {=INDEX(Table3[Codigo Referencia], MATCH(A11, Table3[Nombre cuenta], 0))} -> 0000103 | D11: =SUMIF(September!$I$3:$I$88, A11, September!$B$3:$B$88) -> 0 | E11: =SUMIF(September!$I$3:$I$88, A11, September!$C$3:$C$88) -> 0 | F11: TRUE
C14: Total | D14: =SUM(Current_transactions_2[Total Mensual]) -> 146000 | E14: =SUM(Current_transactions_2[Total quincenal]) -> 73000

Sheet Deuda
A1: Mensualidades
A3: Concepto | B3: Cantidad | C3: # Mensualidades | D3: Mensualidades Pagadas | E3: Mensualidad | F3: Restante | G3: Tarjeta
A4: Gastos Medicos Menores | B4: ='Gastos Medicos Menores'!D60 -> 6354.68 | C4: 1 | D4: 0 | E4: =B4/C4 -> 6354.68 | F4: =B4-(D4*E4) -> 6354.68 | G4: 2Now Gastos
A5: Gastos Generales | B5: ='Gastos Generales'!C84 -> 1736.2 | C5: 1 | D5: 0 | E5: =B5/C5 -> 1736.2 | F5: =B5-(D5*E5) -> 1736.2 | G5: 2Now Gastos
A6: Gastos Medicos Mayores 2Now | B6: ='Gastos Medicos Mayores'!D38 -> 3802 | C6: 1 | D6: 0 | E6: =B6/C6 -> 3802 | F6: =B6-(D6*E6) -> 3802 | G6: 2Now Gastos
A7: Gastos Hogar y Alimentos | B7: ='Gastos Alimentos'!B97 -> 1067.32 | C7: 1 | D7: 0 | E7: =B7/C7 -> 1067.32 | F7: =B7-(D7*E7) -> 1067.32 | G7: 2Now Hogar
A8: Texas 2 | B8: ='Gastos Viaje Texas Dec 25'!B45 -> 18942.52 | C8: 3 | D8: 2 | E8: =B8/C8 -> 6314.1733 | F8: =(C8-D8)*E8 -> 6314.1733 | G8: AMEX
A9: Olinca Enero | B9: 17280 | C9: 3 | D9: 2 | E9: =B9/C9 -> 5760 | F9: =(C9-D9)*E9 -> 5760 | G9: AMEX
A10: Olinca Diciembre | B10: 17280 | C10: 3 | D10: 3 | E10: =B10/C10 -> 5760 | F10: =(C10-D10)*E10 -> 0 | G10: AMEX
A11: Olinca Noviembre | B11: 17280 | C11: 3 | D11: 3 | E11: =B11/C11 -> 5760 | F11: =(C11-D11)*E11 -> 0 | G11: AMEX
A12: AIRBNB | B12: 15024.74 | C12: 3 | D12: 3 | E12: =B12/C12 -> 5008.2467 | F12: =B12-(D12*E12) -> 0 | G12: AMEX
A13: AMEX MSI | B13: 6800 | C13: 9 | D13: 5 | E13: =B13/C13 -> 755.55556 | F13: =(C13-D13)*E13 -> 3022.2222 | G13: AMEX
A14: AMEX Extranjero Dic | B14: =277.93+1303.35+112.81+262.09+1656.25 -> 3612.43 | C14: 3 | D14: 2 | E14: =B14/C14 -> 1204.1433 | F14: =B14-(D14*E14) -> 1204.1433 | G14: AMEX
A15: AMEX | B15: ='Gastos Generales'!C83 -> 0 | C15: 1 | D15: 1 | E15: =(B15/C15)*(C15-D15) -> 0 | F15: =(C15-D15)*E15 -> 0 | G15: AMEX
A16: Gastos Medicos Mayores Amex | B16: ='Gastos Medicos Mayores'!D37 -> 1400 | C16: 1 | D16: 1 | E16: =B16/C16 -> 1400 | F16: =B16-(D16*E16) -> 0 | G16: AMEX
A17: Vuelo Tijuana | B17: 14500 | C17: 3 | D17: 3 | E17: =B17/C17 -> 4833.3333 | F17: =(C17-D17)*E17 -> 0 | G17: AMEX
A18: AMEX Gastos medicos | B18: ='Gastos Medicos Menores'!D59 -> 0 | C18: 1 | D18: 0 | E18: =B18/C18 -> 0 | F18: =B18-(D18*E18) -> 0 | G18: AMEX
A19: Costco | B19: ='Gastos Alimentos'!G97+'Gastos Generales'!C89 -> 0 | C19: 1 | D19: 0 | E19: =(B19/C19)*(C19-D19) -> 0 | F19: =(C19-D19)*E19 -> 0 | G19: Costco
A20: Sala | B20: 37794.6 | C20: 18 | D20: 9 | E20: =B20/C20 -> 2099.7 | F20: =(C20-D20)*E20 -> 18897.3 | G20: HSBC World elite
A21: Texas 1 | B21: ='Gastos Viaje Texas Dec 25'!B12 -> 20555.63 | C21: 6 | D21: 2 | E21: =B21/C21 -> 3425.9383 | F21: =(C21-D21)*E21 -> 13703.753 | G21: HSBC World elite
A22: Happy Holidays | B22: 10246.2 | C22: 6 | D22: 2 | E22: =B22/C22 -> 1707.7 | F22: =(C22-D22)*E22 -> 6830.8 | G22: HSBC World elite
A23: Amazon MSI | B23: 7390.75 | C23: 9 | D23: 3 | E23: =B23/C23 -> 821.19444 | F23: =B23-(D23*E23) -> 4927.1667 | G23: HSBC World elite
A24: Gastos Programados WE | B24: ='Gastos WE'!C65 -> 0 | C24: 1 | D24: 0 | E24: =(B24/C24)*(C24-D24) -> 0 | F24: =(C24-D24)*E24 -> 0 | G24: HSBC World elite
A25: Computadora | B25: 3999 | C25: 6 | D25: 2 | E25: =B25/C25 -> 666.5 | F25: =(C25-D25)*E25 -> 2666 | G25: HSBC World elite
A26: Gastos WE | B26: ='Gastos WE'!G65+'Gastos Medicos Menores'!D61 -> 0 | C26: 1 | D26: 0 | E26: =(B26/C26)*(C26-D26) -> 0 | F26: =(C26-D26)*E26 -> 0 | G26: HSBC World elite
A27: Toys R Us | B27: 2668 | C27: 3 | D27: 2 | E27: =B27/C27 -> 889.33333 | F27: =(C27-D27)*E27 -> 889.33333 | G27: HSBC World elite
A28: iPad | B28: 7653 | C28: 9 | D28: 9 | E28: =B28/C28 -> 850.33333 | F28: =(C28-D28)*E28 -> 0 | G28: HSBC World elite
A29: Master | B29: 4998.84 | C29: 12 | D29: 11 | E29: =B29/C29 -> 416.57 | F29: =(C29-D29)*E29 -> 416.57 | G29: HSBC World elite
A30: Lavadora | B30: 6291 | C30: 9 | D30: 9 | E30: =B30/C30 -> 699 | F30: =(C30-D30)*E30 -> 0 | G30: HSBC World elite
A31: Estufa | B31: 4169 | C31: 9 | D31: 9 | E31: =B31/C31 -> 463.22222 | F31: =(C31-D31)*E31 -> 0 | G31: HSBC World elite
A32: Gastos Medicos WE | B32: ='Gastos Medicos Menores'!D61 -> 0 | C32: 1 | D32: 0 | E32: =B32/C32 -> 0 | F32: =(C32-D32)*E32 -> 0 | G32: HSBC World elite
A33: Bellroy Sling | B33: 3168.41 | C33: 6 | D33: 6 | E33: =B33/C33 -> 528.06833 | F33: =(C33-D33)*E33 -> 0 | G33: HSBC World elite
A34: Dentista | B34: 12244 | C34: 6 | D34: 6 | E34: =B34/C34 -> 2040.6667 | F34: =(C34-D34)*E34 -> 0 | G34: HSBC World elite
A35: La Comer | B35: 13498 | C35: 12 | D35: 12 | E35: =B35/C35 -> 1124.8333 | F35: =(C35-D35)*E35 -> 0 | G35: HSBC World elite
A36: Computadora | B36: 31641.36 | C36: 6 | D36: 1 | E36: =B36/C36 -> 5273.56 | F36: =(C36-D36)*E36 -> 26367.8 | G36: HSBC World elite
A37: Tarjeta Liverpool | B37: ='Gastos Generales'!C85 -> 0 | C37: 1 | D37: 0 | E37: =(B37/C37)*(C37-D37) -> 0 | F37: =(C37-D37)*E37 -> 0 | G37: Liverpool
A38: Tarjeta Nu | B38: ='Gastos Generales'!B88 -> 0 | C38: 1 | D38: 0 | E38: =B38/C38 -> 0 | F38: =B38-(D38*E38) -> 0 | G38: Nu Tarjeta
A39: Tarjeta palacio | B39: ='Gastos Generales'!C86 -> 0 | C39: 1 | D39: 0 | E39: =(B39/C39)*(C39-D39) -> 0 | F39: =(C39-D39)*E39 -> 0 | G39: Palacio de Hierro
A40: Tarjeta Uala | B40: ='Gastos Generales'!C87 -> 8315 | C40: 1 | D40: 0 | E40: =B40/C40 -> 8315 | F40: =B40-(D40*E40) -> 8315 | G40: Uala Credito
A41: Vuelos Houston | B41: 36620 | C41: 6 | D41: 4 | E41: =B41/C41 -> 6103.3333 | F41: =B41-(D41*E41) -> 12206.667 | G41: Volaris
A42: IKEA | B42: 5148 | C42: 6 | D42: 6 | E42: =B42/C42 -> 858 | F42: =B42-(D42*E42) -> 0 | G42: Volaris
A43: Olinca Febrero | B43: 17280 | C43: 3 | D43: 1 | E43: =B43/C43 -> 5760 | F43: =B43-(D43*E43) -> 11520 | G43: AMEX
A44: Tennis Brooks | B44: 3259.08 | C44: 6 | D44: 1 | E44: =B44/C44 -> 543.18 | F44: =B44-(D44*E44) -> 2715.9 | G44: AMEX
A47: Total Deuda | B47: =SUM(B4:B25) -> 205066.07 | E47: Deuda Restante | F47: =SUM(F4:F25) -> 76285.759 | H47: Dia de corte | I47: Dia limite de pago
A49: Total por tarjeta | B49: HSBC World elite | C49: =SUMIF($G$2:$G$47, B49, $F$2:$F$47) -> 74698.723 | E49: Pagos unicos tarjetas | F49: Nu Tarjeta | G49: =SUMIF($G$2:$G$42, F49, $E$2:$E$42) -> 0 | H49: 12 | I49: 2
B50: Nu Tarjeta | C50: =SUMIF($G$2:$G$48, B50, $F$2:$F$48) -> 0 | F50: Volaris | G50: =SUMIFS($E$2:$E$42,$G$2:$G$42, F50, $C$2:$C$42, "=1") -> 0 | H50: 16 | I50: 7
B51: Volaris | C51: =SUMIF($G$2:$G$48, B51, $F$2:$F$48) -> 12206.667 | F51: HSBC World elite | G51: =SUMIFS($E$2:$E$42,$G$2:$G$42, F51, $C$2:$C$42, "=1") -> 0
B52: Palacio de Hierro | C52: =SUMIF($G$2:$G$48, B52, $F$2:$F$48) -> 0 | F52: 2Now Gastos | G52: =SUMIFS($E$2:$E$42,$G$2:$G$42, F52, $C$2:$C$42, "=1") -> 11892.88 | H52: 30 | I52: 14
B53: 2Now Gastos | C53: =SUMIF($G$2:$G$48, B53, $F$2:$F$48) -> 11892.88 | F53: Uala Credito | G53: =SUMIFS($E$2:$E$42,$G$2:$G$42, F53, $C$2:$C$42, "=1") -> 8315 | H53: 11 | I53: 30
B54: AMEX | C54: =SUMIF($G$2:$G$48, B54, $F$2:$F$48) -> 30536.439 | F54: 2Now Hogar | G54: =SUMIFS($E$2:$E$42,$G$2:$G$42, F54, $C$2:$C$42, "=1") -> 1067.32 | H54: 18 | I54: 18
B55: 2Now Hogar | C55: =SUMIF($G$2:$G$48, B55, $F$2:$F$48) -> 1067.32 | F55: Palacio de Hierro | G55: =SUMIFS($E$2:$E$42,$G$2:$G$42, F55, $C$2:$C$42, "=1") -> 0
F56: Costco | G56: =SUMIFS($E$2:$E$42,$G$2:$G$42, F56, $C$2:$C$42, "=1") -> 0 | H56: 27 | I56: 27
F57: Liverpool | G57: =SUMIFS($E$2:$E$42,$G$2:$G$42, F57, $C$2:$C$42, "=1") -> 0 | H57: 16 | I57: 8
F58: AMEX | G58: =SUMIFS($E$2:$E$42,$G$2:$G$42, F58, $C$2:$C$42, "=1") -> 1400
C61: =400000-C54 -> 369463.56 | E61: Meses Sin Intereses
F62: HSBC World elite | G62: =SUMIFS($E$2:$E$25,$G$2:$G$25, F62, $C$2:$C$25, ">1") -> 8721.0328
F63: Volaris | G63: =SUMIFS($E$2:$E$35,$G$2:$G$35, F63, $C$2:$C$35, ">1") -> 0
F64: AMEX | G64: =SUMIFS($E$2:$E$25,$G$2:$G$25, F64, $C$2:$C$25, ">1") -> 35395.452
I66: =18051.01-16170.96 -> 1880.05
A67: =100406.45-C49 -> 25707.727
D71: =400000-341126 -> 58874

Sheet Cuentas
A1: Nombre cuenta | B1: Tipo | C1: Codigo Referencia | D1: Cuenta / Tarjeta | E1: CLABE | J1: Tipos de cuentas
A2: HSBC | B2: Visible | C2: 0000001 | D2: 4069061398 | E2: 021180040690613986 | J2: Ahorro
A3: Santander | B3: Visible | C3: 0000002 | D3: 60567059650 | E3: 014180605670596501 | J3: Visible
A4: BBVA | B4: Visible | C4: 0000003 | D4: 1537717736 | E4: 012180015377177365 | J4: Inversion
A5: Nu Dalia Debito | B5: Visible | C5: 0000004 | E5: 638180010151893079 | J5: Credito
A6: Nu | B6: Visible | C6: 0000005 | D6: 17740419 | E6: 638180000177404193 | J6: Departamental
A7: Stori + | B7: Visible | C7: 0000006 | E7: 646180402300057567
A8: Cetes | B8: Inversion | C8: 0000102 | E8: 135180330008516792
A9: GBM Trading | B9: Inversion | C9: 0000104 | E9: 601180400038253515 | J9: Tipos de gasto
A10: GBM Dolares | B10: Inversion | C10: 0000103 | E10: 601180400049499232 | J10: Estudios y medicamentos
A11: Palacio de Hierro | B11: Departamental | C11: 0000027 | D11: 6620010271451763 | J11: Supermercado
A12: Liverpool | B12: Departamental | C12: 0000029 | E12: 646222162529157954 | J12: Comida para llevar
A13: 2Now Hogar | B13: Credito | C13: 0000022 | D13: 5470748025759733 | E13: 021975211101429027 | J13: Ropa
A14: Rappi | B14: Credito | C14: 0000023 | D14: 4075610085387965 | E14: 646180120624078216 | J14: Servicios
A15: Costco | B15: Credito | C15: 0000024 | E15: 002975010130301365 | J15: Educacion
A16: Volaris | B16: Credito | C16: 0000025 | D16: 5253460005319362 | E16: 059975010021156436 | J16: Actividades
A17: Uala Credito | B17: Credito | C17: 0000025 | J17: Auto
A18: Stori Tarjeta | B18: Credito | C18: 0000026 | D18: 5303460002097136 | E18: 646180224430895806 | J18: Consultas medicas
A19: Nu Tarjeta | B19: Credito | C19: 0000027 | D19: 5267776905329837 | E19: 638975000249369122
A20: HSBC World elite | B20: Credito | C20: 0000028 | D20: 5221748002171250 | E20: 021975211901200792
A21: AMEX | B21: Credito | C21: 0000031 | D21: 371779655281004
A22: 2Now Gastos | B22: Credito | C22: 0000030 | D22: 5470748025758396 | E22: 021975211101429027
A23: HSBC Flexible | B23: Ahorro | C23: 0000011 | E23: 021180065930525793
A24: Nu Cajita Auto | B24: Ahorro | C24: 0000012 | D24: 17740419 | E24: 638180000177404193
A25: Nu Cajita Gastos | B25: Ahorro | C25: 0000013 | D25: 17740419 | E25: 638180000177404193
A26: Nu Cajita Hogar | B26: Ahorro | C26: 0000016 | D26: 17740419 | E26: 638180000177404193
A27: Uala | B27: Ahorro | C27: 0000014 | E27: 138580000023894928
A28: Stori Inversion + | B28: Ahorro | C28: 0000015 | E28: 646180402300057567

Sheet Vacaciones
A1: Cancun Ago 25
A2: Concepto | B2: Monto | C2: Pagado
A3: Hotel Cancun | B3: 27121.12 | C3: Si
A4: Vuelos Cancun | B4: 13536 | C4: Si
A5: Hotel Aeropuerto | B5: 2241.25 | C5: Si
A6: Asientos Vuelo | B6: 1816 | C6: Si
A7: Asientos Vuelo | B7: 1704 | C7: Si
A8: Cena Aeropuerto | B8: 1500 | C8: Si
A9: H&M | B9: 604 | C9: Si
A10: Starbucks Cancun Aeropuerto | B10: 558 | C10: Si
A11: Gasolina Auto Renta | B11: 320.97 | C11: Si
A12: Uber Aeropuerto | B12: 282.58 | C12: Si
A13: Tienda Aeropuerto CUN | B13: 228 | C13: Si
A14: Wifi | B14: 150.85 | C14: Si
A15: Wifi | B15: 148.41 | C15: Si
A16: Renta auto | B16: =3420.5+382.88 -> 3803.38 | C16: Si
B26: =SUM(B3:B20) -> 54014.56

Sheet Gastos Alimentos
A1: 2Now Super | C1: Pagado | D1: Fecha | F1: Costco | H1: Pagado
A2: Concepto | C2: TRUE | F2: Compra mensual | G2: =9959+255 -> 10214 | H2: TRUE
A3: Toks | B3: 672.7 | C3: FALSE | F3: Membresia | G3: 1200 | H3: TRUE
A4: Uber eats | B4: 241.96 | C4: FALSE | F4: Costco | G4: 3891.5 | H4: TRUE
A5: Uber eats | B5: 25.66 | C5: FALSE | F5: Compras casa | G5: 3191.3 | H5: TRUE
A6: Grillo | B6: 127 | C6: FALSE | F6: Anualidad tarjeta | G6: 600 | H6: TRUE
F7: Gastos varios | G7: 2422.1 | H7: TRUE
F8: Alimentos | G8: 165 | H8: TRUE
F9: Compra | G9: 6464.75 | H9: TRUE
F10: Reyes | G10: 2012.65 | H10: TRUE
H11: FALSE
H12: FALSE
H13: FALSE
H14: FALSE
H15: FALSE
H16: FALSE
H17: FALSE
H18: FALSE
H19: FALSE
H20: FALSE
H21: FALSE
H22: FALSE
... H43: FALSE
A96: Total | B96: =SUM(B2:B95) -> 1067.32 | F96: Total | G96: =SUM(G2:G49) -> 30161.3
A97: Por Pagar | B97: =SUMIF(C2:C95, false, B2:B95) -> 1067.32 | F97: Por Pagar | G97: =SUMIF(H2:H64, false, G2:G64) -> 0
A105: Historico
A106: Ago-Sept | F106: Uber eats | G106: 321.69 | H106: TRUE
A107: La comer 17/08 | B107: 3452.76 | C107: TRUE | F107: Uber eats | G107: 30 | H107: TRUE | J107: Sanborns | K107: 36 | L107: TRUE | N107: Mercado | O107: 184 | P107: TRUE
A108: Casa Toño | B108: =576.56+60 -> 636.56 | C108: FALSE | F108: La comer de valle | G108: 602.17 | H108: TRUE | J108: Soriana | K108: 595.6 | L108: TRUE | N108: Santa clara | O108: 100 | P108: TRUE
A109: Oxxo Caseta Oacalco | B109: 157 | C109: TRUE | F109: Oxxo | G109: 79 | H109: TRUE | J109: Santa Clara | K109: 274 | L109: TRUE | N109: Garat | O109: 210 | P109: TRUE
A110: Panda Express | B110: 875 | C110: TRUE | F110: Los Lalos | G110: 586.3 | H110: TRUE | J110: Semillero | K110: 510.4 | L110: TRUE | N110: Los Lalos | O110: 577.5 | P110: TRUE
A111: Grillo | B111: 78 | C111: TRUE | F111: Uber | G111: 109.98 | H111: TRUE | J111: Tierra GARAT | K111: 125 | L111: TRUE | N111: La comer | O111: 3224.3 | P111: TRUE
A112: Desayuno | B112: 234.28 | C112: TRUE | F112: Toks | G112: 535.7 | H112: TRUE | J112: X | K112: 67 | L112: TRUE | N112: Grillo | O112: 48 | P112: TRUE
A113: Cafe | B113: 54 | C113: TRUE | F113: Soriana | G113: 351 | H113: TRUE | J113: Grillo | K113: 113 | L113: TRUE | N113: Uber eats | O113: 50 | P113: TRUE
A114: Starbucks | B114: 400 | C114: TRUE | F114: esperanza | G114: 178 | H114: TRUE | J114: Grillo | K114: 106 | L114: TRUE | N114: Uber eats | O114: 560.43 | P114: TRUE
A115: Uber | B115: 85.7 | C115: TRUE | F115: McDonalds | G115: 579 | H115: TRUE | J115: La comer | K115: 4043.73 | L115: TRUE | N115: Grillo | O115: 68 | P115: TRUE
A116: H&M | B116: 1810 | C116: TRUE | F116: Tommy Pizza | G116: 421 | H116: TRUE | J116: Pasteles CSM | K116: 120 | L116: TRUE | N116: Rincon de ade | O116: 240 | P116: TRUE
A117: Esperanza | B117: 146 | C117: TRUE | F117: Carrito oaxaca | G117: 254 | H117: TRUE | J117: Pasteles CSM | K117: 80 | L117: TRUE | N117: Iguana | O117: 71 | P117: TRUE
A118: Santa Clara | B118: 212 | C118: TRUE | F118: Grillo | G118: 50 | H118: TRUE | J118: Santa Clara | K118: 186 | L118: TRUE | N118: Soriana | O118: 382.27 | P118: TRUE
A119: Uber Chillis | B119: 399.6 | C119: TRUE | F119: Mac donalds | G119: 85 | H119: TRUE | J119: Madraje | K119: 206.8 | L119: TRUE | N119: Los Lalos | O119: 479.6 | P119: TRUE
A120: Starbucks | B120: 50 | C120: TRUE | F120: Grillo | G120: 39 | H120: TRUE | J120: Players CSM | K120: 300 | L120: TRUE | N120: Walmart | O120: 919.23 | P120: TRUE
... A123: Uber Perisur-Casa | B123: 305.71 | C123: TRUE | F123: cafe la comer | G123: 58 | H123: TRUE | J123: Cancino | K123: 896.5 | L123: TRUE | N123: Uber eats | O123: 257.9 | P123: TRUE
A124: Cancino | B124: =655+(655*10%) -> 720.5 | C124: TRUE | D124: 24/08/2025 | F124: Toks Tijuana | G124: 716.3 | H124: TRUE | J124: Los Lalos | K124: 531.3 | L124: TRUE | N124: La comer del valle | O124: 2451.87 | P124: TRUE
A125: Frody | B125: 114 | C125: TRUE | F125: Johny rockets | G125: 159 | H125: TRUE | J125: Santa Clara | K125: 262 | L125: TRUE | N125: Rincon de ade | O125: 445.5 | P125: TRUE
A126: X | B126: 248 | C126: TRUE | F126: Petco | G126: 840 | H126: TRUE | J126: Palomitas palacio | K126: 115 | L126: TRUE | N126: Tierra garat | O126: 192 | P126: TRUE
A127: Cafe C | B127: 1140.7 | C127: TRUE | F127: Best coffe AICM | G127: 240 | H127: TRUE | J127: Tacos La chula | K127: 539 | L127: TRUE | N127: Grillo | O127: 58 | P127: TRUE
A128: Uber Eats | B128: 736.32 | C128: TRUE | F128: LPQ AICM | G128: 68 | H128: TRUE | J128: desayuno | K128: 322 | L128: TRUE | N128: La comer | O128: 1679.16 | P128: TRUE
A129: Starbucks | B129: 50 | C129: TRUE | F129: LPQ AICM | G129: 266.7 | H129: TRUE | J129: Hooters | K129: 457.74 | L129: TRUE | N129: Semillero | O129: 504.9 | P129: TRUE
A130: Soriana | B130: 1763.92 | C130: TRUE | F130: Helados | G130: 224 | H130: TRUE | J130: Tierra Garat | K130: 130 | L130: TRUE | N130: Santa clara | O130: 100 | P130: TRUE
A131: Cafe de hoy | B131: 287.1 | C131: TRUE | F131: Mutti | G131: 145 | H131: TRUE | J131: La comer | K131: 139 | L131: TRUE | N131: Grillo | O131: 75 | P131: TRUE
A132: Uber eats | B132: =668.83+37.14 -> 705.97 | C132: TRUE | F132: Grillo | G132: 90 | H132: TRUE | J132: La comer del valle | K132: 2097.31 | L132: TRUE | N132: Rincon de ade | O132: 220 | P132: TRUE
A133: Crepas | B133: 291 | C133: TRUE | F133: Seven | G133: 81 | H133: TRUE | J133: Uber eats | K133: 508.81 | L133: TRUE | N133: Tierra garat | O133: 299 | P133: TRUE
A134: Desayuno gym viernes | B134: 287.1 | C134: TRUE | F134: Maison Kayser | G134: 308.7 | H134: TRUE | J134: Propina | K134: 10.62 | L134: TRUE | N134: Uber eats | O134: 668.33 | P134: TRUE
A135: Esperanza | B135: 162.5 | C135: TRUE | F135: Grillo | G135: 52 | H135: TRUE | J135: El osito | K135: 512 | L135: TRUE | N135: Uber | O135: 109.99 | P135: TRUE
A136: Soriana | B136: 1077.71 | C136: TRUE | F136: City cafe (COSTCO) | G136: 618.2 | H136: TRUE | J136: La comer | K136: 1885.44 | L136: TRUE | N136: Uber eats | O136: 342.5 | P136: TRUE
A137: Grillo | B137: =137+60+26 -> 223 | C137: TRUE | F137: Desyuno Miguel Laurent | G137: 604 | H137: TRUE | J137: La comer | K137: 251 | L137: TRUE | N137: Uber Eats | O137: 178.02 | P137: TRUE
A138: Starbucks | B138: 250 | C138: TRUE | F138: Cafe dehoy | G138: 296.6 | H138: TRUE | J138: La comer | K138: 118 | L138: TRUE | N138: Grillo | O138: 128 | P138: TRUE
A139: Mutti | B139: 852.5 | C139: TRUE | F139: Los Lalos | G139: 456.5 | H139: TRUE | J139: Little Caesars | K139: 85 | L139: TRUE | N139: Grillo | O139: 60 | P139: TRUE
A140: Uber | B140: 109.8 | C140: TRUE | F140: Rappi | G140: 109 | H140: TRUE | J140: Uber | K140: 189.94 | L140: TRUE | N140: Soriana | O140: 579.1 | P140: TRUE
A141: Mutti | B141: 852.5 | C141: TRUE | F141: El Chaval | G141: 1446.5 | H141: TRUE | J141: Soriana | K141: 638.67 | L141: TRUE | N141: Gasto X | O141: 11 | P141: TRUE
A142: CAncino | B142: 1116.5 | C142: TRUE | F142: La comer | G142: 1514.75 | H142: TRUE | J142: 7 eleven | K142: 61.5 | L142: TRUE | N142: Decoraciones | O142: 538 | P142: TRUE
A143: Oxxo | B143: 297.5 | C143: TRUE | F143: La comer | G143: 337.72 | H143: TRUE | J143: YAG*UNIFSOTO | K143: 90 | L143: TRUE | N143: jamaica | O143: 150 | P143: TRUE
A144: Rappi | B144: 614.7 | C144: TRUE | F144: La comer | G144: 60 | H144: TRUE | J144: Grillo | K144: 47 | L144: TRUE | N144: tierra garat | O144: 216 | P144: TRUE
A145: La comer | B145: 1230.94 | C145: TRUE | F145: La comer | G145: 1096.71 | H145: TRUE | J145: Uber eats | K145: 640.5 | L145: TRUE | N145: Uber eats | O145: 1627 | P145: TRUE
A146: La comer | B146: 2273.61 | C146: TRUE | F146: Grillo | G146: 64 | H146: TRUE | J146: Uber eats propina | K146: 34.67 | L146: TRUE | N146: Garabatos | O146: 294 | P146: TRUE
A147: Carnitas | B147: 270 | C147: TRUE | F147: La comer | G147: 2042.46 | H147: TRUE | J147: X | K147: 17.36 | L147: TRUE | N147: La comer | O147: 1970.31 | P147: TRUE
A148: La comer 12/09 | B148: 3098.7 | C148: TRUE | F148: Croquetas | G148: =671.88+15 -> 686.88 | H148: TRUE | J148: Costco | K148: 4010.43 | L148: TRUE | N148: Uber eats | O148: 169.75 | P148: TRUE
A149: Cafe comer | B149: 200 | C149: TRUE | F149: Grillo | G149: 212 | H149: TRUE | J149: Tierra Garat | K149: 79 | L149: TRUE | N149: Italiannis | O149: 715 | P149: TRUE
A150: Chilis | B150: 551.19 | C150: TRUE | F150: Rincon de ade | G150: 352 | H150: TRUE | J150: Uber | K150: 119.98 | L150: TRUE | N150: tierra garat | O150: 130 | P150: TRUE
A151: Grillo | B151: 382 | C151: TRUE | F151: Little Caesar | G151: 319.64 | H151: TRUE | J151: Contenedor | K151: 221 | L151: TRUE | N151: Carrito | O151: 297 | P151: TRUE
A152: Desayuno Rincon de Ade | B152: 230 | C152: TRUE | F152: Uber eats | G152: =271.61+15.8 -> 287.41 | H152: TRUE | J152: uber | K152: 75.37 | L152: TRUE | N152: Grillo | O152: 101 | P152: TRUE
A153: Comer | B153: 269 | C153: TRUE | F153: La comer | G153: 2208.65 | H153: TRUE | J153: Soriana | K153: 179.31 | L153: TRUE | N153: La comer cafe | O153: 62 | P153: TRUE
A154: Uber | B154: 119 | C154: TRUE | F154: Uber eats | G154: 824.65 | H154: TRUE | J154: 7 Eleven | K154: 88.5 | L154: TRUE | N154: La comer | O154: 2507 | P154: TRUE
A155: Mercado Pago | B155: 90 | C155: TRUE | F155: Lumen | G155: 122 | H155: TRUE | J155: Restaurante Almara | K155: 665.5 | L155: TRUE | N155: Uber eats | O155: 324.61 | P155: TRUE
A156: Los Lalos | B156: 440 | C156: TRUE | F156: Rincon de ade | G156: 341 | H156: TRUE | I156: Corte Oct 16 | J156: Cancino | K156: 693 | L156: TRUE | N156: tierra garat | O156: 163 | P156: TRUE
A157: amazon | B157: 183.6 | C157: TRUE | J157: Grillo | K157: 86 | L157: TRUE | N157: Mandrake | O157: 183.7 | P157: TRUE
A158: Grillo | B158: 286 | C158: TRUE | J158: Miniso | K158: 99.9 | L158: TRUE | N158: Mollets | O158: 155 | P158: TRUE
A159: la comer | B159: 200 | C159: TRUE | J159: Starbucks | K159: 101 | L159: TRUE | N159: Soriana | O159: 146.3 | P159: TRUE
A160: la comer | B160: 3098.7 | C160: TRUE | J160: Lavado | K160: 250 | L160: TRUE | N160: La comer | O160: 2811.2 | P160: TRUE
A161: Grillo | B161: 220 | C161: TRUE | J161: Grillo | K161: 100 | L161: TRUE | N161: la comer cafe | O161: 146 | P161: TRUE
A162: La comer | B162: 3426.43 | C162: TRUE | J162: La comer | K162: 3259.02 | L162: TRUE | N162: Uber eats | O162: 592.66 | P162: TRUE
A163: Ztl | B163: 180 | C163: TRUE | J163: Cafe Coyoacan | K163: =93+200 -> 293 | L163: TRUE | N163: Uber eats | O163: 184.11 | P163: TRUE
A164: Garabatos | B164: 102 | C164: TRUE | D164: Corte 16 de Sept | J164: Lumen | K164: 13.5 | L164: TRUE | N164: tierra garat | O164: 100.52 | P164: TRUE
J165: Rincon de ade | K165: 379.5 | L165: TRUE
J166: Ferreteria | K166: 120 | L166: TRUE
J167: 7 Eleven | K167: 30 | L167: TRUE
J168: Uber Eats | K168: 89.95 | L168: TRUE
J171: Uber | K171: 89.95 | L171: TRUE

Sheet Gastos Generales
A1: Concepto | B1: Monto | C1: Pagado | D1: Tarjeta Usada
A2: Zapatos Leander | B2: 670 | C2: TRUE | D2: Palacio de Hierro
A3: Heladeria Roxy | B3: 392.7 | C3: TRUE | D3: AMEX
A4: Gasolina | B4: 1210.24 | C4: TRUE | D4: 2Now Gastos
A5: Amazon | B5: 237.2 | C5: FALSE | D5: 2Now Gastos
A6: Amazon bomba | B6: 1499 | C6: FALSE | D6: 2Now Gastos
A7: Labial Dalia | B7: 920 | C7: TRUE | D7: Liverpool
A8: Peluqueria Lean | B8: 215 | C8: TRUE | D8: Liverpool
A9: Amazon | B9: 392 | C9: TRUE | D9: AMEX
A10: Amazon | B10: 359 | C10: TRUE | D10: AMEX
A11: Amazon | B11: 329.69 | C11: TRUE | D11: AMEX
A12: Amazon | B12: 325.59 | C12: TRUE | D12: AMEX
A13: Playstation | B13: 246.22 | C13: TRUE | D13: AMEX
... A25: Natacion | B25: 3000 | C25: FALSE | D25: Uala Credito
H28: =B22+B21 -> 1978
H30: =(H28*0.1)/365 -> 0.54191781
H31: =H30*22 -> 11.922192
B82: Total Gastado | C82: Total por pagar
A83: AMEX | B83: =SUMIF(D$2:D78,A83,B$2:B78) -> 3984.82 | C83: =SUMIFS(B$2:B78,C$2:C78,false,D$2:D78,A83) -> 0
A84: 2Now Gastos | B84: =SUMIF(D$2:D79,A84,B$2:B79) -> 2946.44 | C84: =SUMIFS(B$2:B79,C$2:C79,false,D$2:D79,A84) -> 1736.2
A85: Liverpool | B85: =SUMIF(D$2:D80,A85,B$2:B80) -> 1135 | C85: =SUMIFS(B$2:B80,C$2:C80,false,D$2:D80,A85) -> 0
A86: Palacio de Hierro | B86: =SUMIF(D$2:D81,A86,B$2:B81) -> 670 | C86: =SUMIFS(B$2:B81,C$2:C81,false,D$2:D81,A86) -> 0
A87: Uala Credito | B87: =SUMIF(D$2:D82,A87,B$2:B82) -> 8315 | C87: =SUMIFS(B$2:B82,C$2:C82,false,D$2:D82,A87) -> 8315
A88: Nu | B88: =SUMIF(D$2:D83,A88,B$2:B83) -> 0 | C88: =SUMIFS(B$2:B83,C$2:C83,false,D$2:D83,A88) -> 0
A89: Costco | B89: =SUMIF(D$2:D84,A89,B$2:B84) -> 18945 | C89: =SUMIFS(B$2:B84,C$2:C84,false,D$2:D84,A89) -> 0
A92: Historico | N92: Historico AMEX
A93: Ago-Sept | E93: Sept-Oct | I93: Dic-Ene | N93: Ferreteria Fusibles | O93: 576 | P93: TRUE | R93: Historico
A94: Cafe la comer | B94: 129 | C94: TRUE | E94: Ihop | F94: 1012 | G94: TRUE | I94: La comer | J94: 3004.52 | K94: TRUE | L94: 2Now Gastos | N94: La comer cafe | O94: 56 | P94: TRUE | R94: uber | S94: 47.31 | T94: TRUE | U94: 2Now Gastos
A95: Uber | B95: 126.21 | C95: TRUE | E95: Dairy Queen | F95: 148 | G95: TRUE | I95: Uber | J95: 49.95 | K95: TRUE | L95: 2Now Gastos | N95: La comer Cafe | O95: 129 | P95: TRUE | R95: Farmacia | S95: 193 | T95: TRUE | U95: 2Now Gastos
A96: Rappi | B96: 207.8 | C96: TRUE | E96: Gasolina | F96: 1176.13 | G96: TRUE | I96: Flores Dalia | J96: 820.65 | K96: TRUE | L96: 2Now Gastos | N96: Oxxo | O96: 47 | P96: TRUE | R96: uber | S96: 64.09 | T96: TRUE | U96: 2Now Gastos
A97: Uber | B97: 126.21 | C97: TRUE | E97: Oxxo | F97: 116 | G97: TRUE | I97: Gasolina | J97: 1023.72 | K97: TRUE | L97: 2Now Gastos | N97: Petco | O97: 715 | P97: TRUE | R97: Motrin y alasol | S97: 359 | T97: TRUE | U97: 2Now Gastos
A98: Lumen | B98: 200 | C98: TRUE | E98: Fotos visa | F98: 240 | G98: TRUE | I98: Santa Clara | J98: 482 | K98: TRUE | L98: 2Now Gastos | N98: Mantenimiento Auto | O98: 4500 | P98: TRUE | R98: Cremas neutrogena | S98: 421.2 | T98: TRUE | U98: 2Now Gastos
A99: Petco | B99: 357.5 | C99: TRUE | E99: Waldos | F99: 147.94 | G99: TRUE | I99: Amazon | J99: 333 | K99: TRUE | L99: 2Now Gastos | N99: Sfera | O99: 827 | P99: TRUE | R99: Moneypool | S99: 31.17 | T99: TRUE | U99: 2Now Gastos
A100: Grillo | B100: 32 | C100: TRUE | E100: uber | F100: 57.94 | G100: TRUE | I100: Uber | J100: 99.96 | K100: TRUE | L100: 2Now Gastos | N100: Zara | O100: 1665 | P100: TRUE | R100: Lumen | S100: 6.5 | T100: TRUE | U100: 2Now Gastos
A101: Grillo | B101: 107 | C101: TRUE | E101: Uber | F101: 240.81 | G101: TRUE | I101: Uber | J101: 89.94 | K101: TRUE | L101: 2Now Gastos | N101: Gap | O101: 319.2 | P101: TRUE | R101: Lumen | S101: 399.9 | T101: TRUE | U101: 2Now Gastos
A102: Cafe San Pedro | B102: 266 | C102: TRUE | E102: Veterinario | F102: 405 | G102: TRUE | I102: Uber | J102: 99.97 | K102: TRUE | L102: 2Now Gastos | N102: Tiendita olinca | O102: 100 | P102: TRUE | R102: Tempra | S102: 225.5 | T102: TRUE | U102: 2Now Gastos
A103: Pediasure e Ibuprofeno | B103: 293.5 | C103: TRUE | E103: Grillo | F103: 40 | G103: TRUE | I103: Uber | J103: 79.97 | K103: TRUE | L103: 2Now Gastos | N103: Cinnabon | O103: 375 | P103: TRUE | R103: Gasolina | S103: 1256.82 | T103: TRUE | U103: 2Now Gastos
A104: Maison Kayser | B104: 251 | C104: TRUE | E104: Antibiotico | F104: 428 | G104: TRUE | I104: Uber | J104: 368.71 | K104: TRUE | L104: 2Now Gastos | N104: Starbucks | O104: 111 | P104: TRUE | R104: Verificacion | S104: 666 | T104: TRUE | U104: 2Now Gastos
A105: Maison Kayser | B105: 58.8 | C105: TRUE | E105: Oxxo | F105: 10 | G105: TRUE | I105: Gasolina | J105: 1247.65 | K105: TRUE | L105: 2Now Gastos | N105: Wifi Avion | O105: 151.03 | P105: TRUE | R105: Rappi | S105: 313.18 | T105: TRUE | U105: AMEX
A106: La comer | B106: 142 | C106: TRUE | E106: Uber | F106: 119.37 | G106: TRUE | I106: Rappi | J106: =333.9 -> 333.9 | K106: TRUE | L106: 2Now Gastos | N106: Inscripcion Gimnasia | O106: 2500 | P106: TRUE | R106: Tierra Garat | S106: 76 | T106: TRUE | U106: AMEX
A107: Pegalinas | B107: 523.2 | C107: TRUE | E107: PS Plus | F107: 270.44 | G107: TRUE | I107: Kidzania | J107: 2293 | K107: TRUE | L107: AMEX | N107: Tiendita olinca | O107: 200 | P107: TRUE | R107: Starbucks | S107: 111 | T107: TRUE | U107: AMEX
A108: Petco | B108: 224.3 | C108: TRUE | E108: Uber | F108: 100.51 | G108: TRUE | I108: Tiendita olinca | J108: 52 | K108: TRUE | L108: AMEX | N108: Esperanza | O108: 215 | P108: TRUE | R108: Starbucks | S108: 422 | T108: TRUE | U108: AMEX
A109: Uber | B109: 118.98 | C109: TRUE | E109: Uber | F109: 124.14 | G109: TRUE | I109: Mercado libre | J109: 379.1 | K109: TRUE | L109: AMEX | N109: Amazon | O109: 319.9 | P109: TRUE | R109: Tiendita olinca | S109: 85 | T109: TRUE | U109: AMEX
A110: Cafe | B110: 76.96 | C110: TRUE | E110: Uber | F110: =35.07+39.24 -> 74.31 | G110: TRUE | I110: La comer | J110: 149 | K110: TRUE | L110: AMEX | N110: Kindle | O110: 16.43 | P110: TRUE | R110: HM | S110: 597 | T110: TRUE | U110: AMEX
A111: Ikea | B111: 377 | C111: TRUE | E111: seven | F111: 63 | G111: TRUE | K111: TRUE | L111: AMEX | N111: Amazon DE | O111: 39.06 | P111: TRUE | R111: HM | S111: 598 | T111: TRUE | U111: AMEX
A112: Lapicera | B112: 297 | C112: TRUE | E112: Gasolina | F112: 1173.77 | G112: TRUE | I112: Santa Clara | J112: 100 | K112: TRUE | L112: AMEX | N112: Amazon DE | O112: 16.19 | P112: TRUE | R112: Play station | S112: 262.69 | T112: TRUE | U112: AMEX
A113: Kit limpieza | B113: 714 | C113: TRUE | E113: Uber | F113: 97.56 | G113: TRUE | I113: Little Kickers | J113: 1187 | K113: TRUE | L113: Uala Credito | N113: Zoho Sub | O113: 250.56 | P113: TRUE | R113: Libros | S113: 6340 | T113: TRUE | U113: Uala Credito
A114: Alpecin azul | B114: 499 | C114: TRUE | E114: Amazon | F114: 326.13 | G114: TRUE | I114: Fotos Navidad | J114: 425 | K114: TRUE | L114: 2Now Gastos | N114: Tiendita olinca | O114: 129 | P114: TRUE | R114: Gas | S114: 2000 | T114: TRUE | U114: 2Now Gastos
A115: Botella Frozen | B115: 406 | C115: TRUE | E115: Uber | F115: 115.88 | G115: TRUE | I115: Uber eats | J115: 211.88 | K115: TRUE | L115: 2Now Gastos | R115: Dentalia | S115: 350 | T115: TRUE | U115: 2Now Gastos
A116: Helados Perisur | B116: 252 | C116: TRUE | D116: 22/08/2025 | E116: Amazon | F116: 668.17 | G116: TRUE | I116: Grillo | J116: 151 | K116: TRUE | L116: 2Now Gastos | R116: Ofrendas | S116: 232.74 | T116: TRUE | U116: 2Now Gastos
A117: Corte Leander | B117: 270 | C117: TRUE | D117: 23/08/2025 | E117: Tierra Garat | F117: 168 | G117: TRUE | I117: Happy swimm | J117: 2540 | K117: TRUE | L117: Uala Credito | R117: Universum | S117: 120 | T117: TRUE | U117: 2Now Gastos
A118: Gas | B118: 0 | C118: TRUE | E118: San pablo | F118: 100 | G118: TRUE | I118: Uber eats | J118: 537.22 | K118: TRUE | L118: 2Now Gastos | R118: Lumen | S118: =128.5+32.5 -> 161 | T118: TRUE | U118: 2Now Gastos
A119: Starbucks | B119: 87 | C119: TRUE | E119: San pablo | F119: 338 | G119: TRUE | I119: 7 Eleven | J119: 45 | K119: TRUE | L119: 2Now Gastos | R119: Croquetas y cepillos de dientes | S119: 2492 | T119: TRUE | U119: AMEX
A120: Sears ICEE | B120: 65 | C120: TRUE | E120: San pablo | F120: 45 | G120: TRUE | I120: Uber | J120: 209.71 | K120: TRUE | L120: 2Now Gastos | R120: Comida Berlin | S120: 285 | T120: TRUE | U120: AMEX
A121: Starbucks | B121: 295 | C121: TRUE | E121: Uber | F121: 78 | G121: TRUE | I121: Netflix | J121: 398 | K121: TRUE | L121: 2Now Gastos | R121: Tiendita olinca | S121: 50 | T121: TRUE | U121: Nu
A122: Frody | B122: 96 | C122: TRUE | E122: Uber | F122: 81.91 | G122: TRUE | I122: Garabatos | J122: 174.75 | K122: TRUE | L122: 2Now Gastos | R122: Netflix | S122: 398 | T122: TRUE | U122: 2Now Gastos
A123: AMazon | B123: 592.49 | C123: TRUE | E123: Rappi (pruebas covid) | F123: 623.9 | G123: TRUE | I123: Star Medica | J123: 190.3 | K123: TRUE | L123: 2Now Gastos | R123: Enterogermina | S123: 552 | T123: TRUE | U123: 2Now Gastos
A124: Starbucks | B124: 87 | C124: TRUE | E124: Soriana | F124: 24.9 | G124: TRUE | I124: La comer | J124: 142 | K124: TRUE | L124: 2Now Gastos | R124: Happy swimm | S124: 2540 | T124: TRUE | U124: Uala Credito
A125: Gatorade | B125: 22 | C125: TRUE | E125: Ferreteria | F125: 85.06 | G125: TRUE | I125: Kits nebulizacion | J125: 218 | K125: TRUE | L125: 2Now Gastos | R125: PRO-K Gimnasia | S125: 2000 | T125: TRUE | U125: Uala Credito
A126: Neutrogena cremas | B126: 401.4 | C126: TRUE | E126: Netflix | F126: 398 | G126: TRUE | I126: Tiendita olinca | J126: 70 | K126: TRUE | L126: AMEX | R126: Starbucks | S126: 78 | T126: TRUE | U126: 2Now Gastos
A127: Netflix | B127: 398 | C127: TRUE | E127: Rappi Lysol | F127: 245.5 | G127: TRUE | I127: Tierra garat | J127: 135 | K127: TRUE | L127: AMEX | R127: Fantasias Miguel | S127: 214.54 | T127: TRUE | U127: 2Now Gastos
A128: Home depot general | B128: 1092 | C128: TRUE | E128: Uber | F128: 56.52 | G128: TRUE | I128: Kidzania | J128: 135 | K128: TRUE | L128: AMEX | R128: Bisquets | S128: 248 | T128: TRUE | U128: 2Now Gastos
A129: Home Depot Electricidad | B129: 1557.96 | C129: TRUE | E129: Uber | F129: 61.8 | G129: TRUE | I129: Kidzania | J129: 59 | K129: TRUE | L129: AMEX | R129: Regalos Nico y Carlota | S129: 726 | T129: TRUE | U129: 2Now Gastos
A130: 7 Eleven | B130: 104 | C130: TRUE | E130: ShakeShack | F130: 965.12 | G130: TRUE | I130: Televia | J130: 200 | K130: TRUE | L130: AMEX | R130: Gasolina | S130: 1232.84 | T130: TRUE | U130: 2Now Gastos
... A132: Grillo | B132: 58 | C132: TRUE | E132: Uber Eats | F132: 92.1 | G132: TRUE | I132: Mas gastos | J132: 1610.41 | K132: TRUE | L132: AMEX | R132: Palacio Cafe | S132: 174 | T132: TRUE | U132: 2Now Gastos
A133: Grillo | B133: 82 | C133: TRUE | D133: Corte 12 Sept | E133: Crepa y cafe | F133: 115 | G133: TRUE | H133: Corte12 Oct | I133: Esperanza | J133: 165.5 | K133: TRUE | L133: AMEX | R133: Esperanza | S133: 165.5 | T133: TRUE | U133: AMEX
I134: 7 Eleven Adolfo | J134: 105 | K134: TRUE | L134: AMEX | R134: Starbucks | S134: 176 | T134: TRUE | U134: AMEX
I135: Costco | J135: 97.16 | K135: TRUE | L135: AMEX | R135: Esperanza | S135: 162 | T135: TRUE | U135: AMEX
I136: Esperanza | J136: 273 | K136: TRUE | L136: AMEX | R136: Barberia | S136: 750 | T136: TRUE | U136: AMEX
I137: Olinca | J137: 480 | K137: TRUE | L137: AMEX | R137: Starbucs | S137: 171 | T137: TRUE | U137: AMEX
I138: Starbucks | J138: 112 | K138: TRUE | L138: AMEX | R138: Wifi Aeromexico | S138: 188.2 | T138: TRUE | U138: AMEX
I139: Santa clara | J139: 130 | K139: TRUE | L139: AMEX | R139: Tienda Olinca | S139: 50 | T139: TRUE | U139: AMEX
I140: Kidzania | J140: 118 | K140: TRUE | L140: AMEX | R140: Rappi | S140: 284.5 | T140: TRUE | U140: AMEX
I141: Barberia | J141: 750 | K141: TRUE | L141: AMEX | R141: Cafe palacio | S141: 174 | T141: TRUE | U141: 2Now Gastos
I142: Tiendita olinca | J142: 100 | K142: TRUE | L142: AMEX | R142: La comer cafe | S142: 142 | T142: TRUE | U142: 2Now Gastos
I143: Helado mitikah | J143: 109 | K143: TRUE | L143: 2Now Gastos | R143: Bolsa Dalia | S143: 1603 | T143: TRUE | U143: Palacio de Hierro
I144: UNIQLO | J144: =H4 | K144: TRUE | L144: AMEX
I145: Uber | J145: 79.97 | K145: TRUE | L145: 2Now Gastos
I146: Gasolina | J146: 1153.28 | K146: TRUE | L146: 2Now Gastos
I147: Super clime | J147: 268 | K147: TRUE | L147: 2Now Gastos
I148: Esperanza | J148: 180 | K148: TRUE | L148: 2Now Gastos
I149: Esperanza | J149: 160 | K149: TRUE | L149: 2Now Gastos
I150: Farmacia del ahorro | J150: 215 | K150: TRUE | L150: 2Now Gastos
I151: Starmedica rest | J151: 193.3 | K151: TRUE | L151: 2Now Gastos

Sheet Gastos WE
A1: Gastos Programados | C1: Pagado | E1: Otros Gastos | F1: Monto | G1: Pagado | H1: Fecha
A2: sports world | B2: 5005 | C2: TRUE | G2: TRUE
A3: Totalplay | B3: 1190 | C3: TRUE | G3: FALSE
A4: Digital ocean | B4: =IFERROR(__xludf.DUMMYFUNCTION("GOOGLEFINANCE(""CURRENCY:USDMXN"")*6"),103.30260000000001) -> 103.3026 | C4: TRUE | G4: FALSE
A5: Telefonica | B5: 940 | C5: TRUE | G5: FALSE
A6: Claude | B6: =IFERROR(__xludf.DUMMYFUNCTION("GOOGLEFINANCE(""CURRENCY:USDMXN"")*20"),344.34200000000004) -> 344.342 | C6: TRUE | G6: FALSE
A7: HBO Max | B7: 199 | C7: TRUE | G7: FALSE
A8: Electricidad | B8: 1171 | C8: TRUE | G8: FALSE
A9: Agua | B9: 349 | C9: TRUE
C10: FALSE
C11: FALSE
C12: FALSE
C13: FALSE
C14: FALSE
C15: FALSE
C16: FALSE
C17: FALSE
C18: FALSE
C19: FALSE
C20: FALSE
C21: FALSE
C22: FALSE
C64: Por Pagar | G64: Por Pagar
B65: =SUM(B2:B32) -> 9301.6446 | C65: =SUMIF(C2:C34, false, B2:B34) -> 0 | F65: =SUM(F2:F63) -> 0 | G65: =SUMIF(G2:G63, false, F2:F63) -> 0
F68: =F65+B65 -> 9301.6446
A76: Historico
A77: Hasta 17 Nov | E77: Hasta 17 Ene
A78: Olinca | B78: 17280 | C78: TRUE | E78: Portacables | F78: =1040.93-F94-F95 -> 249 | G78: TRUE | H78: 45982
A79: Bicicletas | B79: 8598 | C79: TRUE | E79: PortaPasteles | F79: 277 | G79: TRUE | H79: 45994
A80: Olinca (Uniformes, licencias) | B80: 3300 | C80: TRUE | E80: Accesorios pasteles | F80: 279 | G80: TRUE | H80: 45994
A81: Olinca (Uniformes, licencias) | B81: 3300 | C81: TRUE | E81: Cera | F81: =119*2 -> 238 | G81: TRUE | H81: 45992
A82: Avion Tijuana | B82: 2899.58 | C82: TRUE | E82: adaptadores micro-usb | F82: 115.3 | G82: TRUE | H82: 45992
A83: Podologia | B83: 2886 | C83: TRUE | E83: Aceite y desmaquillante | F83: 249.85 | G83: TRUE | H83: 45992
A84: IKEA | B84: 2555 | C84: TRUE | E84: Pastel Lena | F84: 1580 | G84: TRUE | H84: 45993
A85: Zara | B85: 2127 | C85: TRUE | E85: Comida Cine | F85: 680 | G85: TRUE | H85: 45991
A86: Toys R Us Perisur | B86: 2067 | C86: TRUE | E86: Posada Suizo | F86: 1558.5 | G86: TRUE | H86: 45992
A87: Lefties | B87: 1942 | C87: TRUE | E87: La comer | F87: 90 | G87: TRUE | H87: 45992
A88: Apple | B88: 1599 | C88: TRUE | E88: Boletos Cine | F88: 333 | G88: TRUE | H88: 45991
A89: Gas | B89: 1500 | C89: TRUE | E89: Juguetron | F89: 45 | G89: TRUE | H89: 45991
A90: Spa | B90: 1198 | C90: TRUE | E90: Ferreteria | F90: 144 | G90: TRUE | H90: 45990
A91: Luces | B91: 999.09 | C91: TRUE | E91: H&M Mancar | F91: 2019.3 | G91: TRUE | H91: 45988
A92: Zara | B92: 999 | C92: TRUE | E92: Libro Leander Advent y Emocionario | F92: 539 | G92: TRUE | H92: 45985
A93: Titans | B93: 936.86 | C93: TRUE | E93: Oxxo Yautepec | F93: 353.5 | G93: TRUE | H93: 45983
... A124: Pediasure | B124: 1011.15 | C124: TRUE | E124: Palacio de hierro | F124: 2204.3 | G124: TRUE | H124: 46018
A125: Labial | B125: 184 | C125: TRUE | E125: Toys R Us | F125: =2668-1869 -> 799 | G125: TRUE | H125: 46019
A126: Apple arcade | B126: 99 | C126: TRUE | E126: Amazon | F126: 229 | G126: TRUE | H126: 46019
A127: Apple tv+ | B127: 129 | C127: TRUE | E127: Amazon | F127: 135 | G127: TRUE | H127: 46019
A128: Zara home | B128: 571 | C128: TRUE
A129: Coursera | B129: 946.89 | C129: TRUE
A130: Universum | B130: 404 | C130: TRUE
A131: Taquearte | B131: 1328.8 | C131: TRUE
A132: Cinnabon | B132: 375 | C132: TRUE
A133: Cafe hotel | B133: 88.19 | C133: TRUE
A134: Trader Joes | B134: 500.27 | C134: TRUE
A135: Helado Santana Row | B135: 146.93 | C135: TRUE
A136: Blue bottle | B136: 96.73 | C136: TRUE
A137: Mosquitero | B137: 299.99 | C137: TRUE
A138: Amazon | B138: 1040.93 | C138: TRUE

Sheet Gastos Medicos Menores
A1: Medicamentos y Consultas | C1: Facturado | D1: Subido a Risco | E1: Reembolsado | F1: Pagado | G1: Tarjeta Usada | H1: Suma A reembolsar
A2: Medicinas Dalia | B2: 1044 | C2: Si | D2: Si | E2: Si | F2: TRUE | G2: 2Now Gastos | H2: =B2*0.9 -> 939.6
A3: Ginecologa | B3: 1500 | C3: Si | D3: Si | E3: Si | F3: TRUE | G3: 2Now Gastos | H3: =B3*0.9 -> 1350
A4: Vacuna Alfredo | B4: 2500 | C4: Si | D4: Si | E4: Si | F4: TRUE | G4: 2Now Gastos | H4: =B4*0.9 -> 2250
A5: Alergologo Leander | B5: 1500 | C5: Si | D5: Si | E5: Si | F5: TRUE | G5: 2Now Gastos | H5: =B5*0.9 -> 1350
A6: Blaxitec | B6: 476 | C6: Si | D6: Si | E6: Si | F6: TRUE | G6: 2Now Gastos | H6: =B6*0.9 -> 428.4
A7: Medicinas Alfredo | B7: 593 | C7: Si | D7: Si | E7: Si | F7: TRUE | G7: 2Now Gastos | H7: =B7*0.9 -> 533.7
A8: Podologa | B8: 1986 | C8: Si | F8: TRUE | G8: 2Now Gastos | H8: =B8*0.9 -> 1787.4
A9: Vacuna Lena | B9: 1700 | C9: Si | D9: Si | E9: Si | F9: TRUE | G9: 2Now Gastos | H9: =B9*0.9 -> 1530
A10: Laser Onicomicosis | B10: 6800 | C10: Si | D10: Si | E10: Si | F10: TRUE | G10: AMEX | H10: =B10*0.9 -> 6120
A11: Estudios Lena y Leander | B11: =3187+2583.99 -> 5770.99 | C11: Si | D11: Si | E11: Si | F11: TRUE | G11: AMEX | H11: =B11*0.9 -> 5193.891
A12: Ferricol | B12: 436 | C12: Si | F12: TRUE | G12: 2Now Gastos | H12: =B12*0.9 -> 392.4
A13: Vacuna Alfredo | B13: 2500 | C13: Si | D13: Si | E13: Si | F13: TRUE | G13: 2Now Gastos | H13: =B13*0.9 -> 2250
A14: Radiografia Chopo | B14: 594.3 | F14: TRUE | G14: AMEX | H14: =B14*0.9 -> 534.87
A15: Radiografia Lab Polanco | B15: 913 | C15: Si | D15: Si | E15: Si | F15: TRUE | G15: AMEX | H15: =B15*0.9 -> 821.7
A16: Radiografias StarMedica | B16: 3261.21 | C16: Si | D16: Si | E16: Si | F16: TRUE | G16: AMEX | H16: =B16*0.9 -> 2935.089
A17: Crema | B17: 350 | C17: Si | F17: TRUE | G17: AMEX | H17: =B17*0.9 -> 315
A18: Consulta Alergologo | B18: 1500 | C18: Si | D18: Si | E18: Si | F18: TRUE | G18: AMEX | H18: =B18*0.9 -> 1350
A19: Combivent Rescate | B19: 1236 | C19: Si | D19: Si | E19: Si | F19: TRUE | G19: 2Now Gastos | H19: =B19*0.9 -> 1112.4
A20: Medicinas nebulizador | B20: 1183 | C20: Si | D20: Si | E20: Si | F20: TRUE | G20: 2Now Gastos | H20: =B20*0.9 -> 1064.7
A21: Antibiotico | B21: 748 | C21: Si | F21: TRUE | G21: AMEX | H21: =B21*0.9 -> 673.2
A22: Vacuna Varicela y Sarampion | B22: 2600 | C22: Si | D22: Si | E22: Si | F22: TRUE | G22: 2Now Gastos | H22: =B22*0.9 -> 2340
A23: Vacuna Varicela | B23: 1650 | C23: Si | D23: Si | E23: Si | F23: TRUE | G23: 2Now Gastos | H23: =B23*0.9 -> 1485
A24: Podologa | B24: 538 | C24: Si | F24: TRUE | G24: 2Now Gastos | H24: =B24*0.9 -> 484.2
A25: Medicinas | B25: 1028 | C25: Si | F25: TRUE | G25: AMEX | H25: =B25*0.9 -> 925.2
A26: Antibiotico | B26: 461 | C26: Si | F26: TRUE | G26: AMEX | H26: =B26*0.9 -> 414.9
A27: Medicinas | B27: 456 | C27: Si | F27: TRUE | G27: 2Now Gastos | H27: =B27*0.9 -> 410.4
A28: Vacuna Alfredo | B28: 2500 | C28: Si | D28: Si | E28: Si | F28: TRUE | G28: AMEX | H28: =B28*0.9 -> 2250
A29: Cita psicologa | B29: 600 | F29: TRUE | G29: HSBC World elite | H29: =B29*0.9 -> 540
A30: Podologa | B30: 538 | C30: Si | D30: Si | E30: Si | F30: TRUE | G30: AMEX | H30: =B30*0.9 -> 484.2
A31: Pulmicort y kits | B31: =682+170 -> 852 | C31: Si | D31: Si | E31: Si | F31: TRUE | G31: 2Now Gastos | H31: =B31*0.9 -> 766.8
A32: Medicinas garganta | B32: 2096.5 | C32: Si | D32: Si | E32: Si | F32: TRUE | G32: AMEX | H32: =B32*0.9 -> 1886.85
A33: Ferricol | B33: 436 | F33: TRUE | G33: AMEX | H33: =B33*0.9 -> 392.4
A34: Vannair | B34: 1219 | C34: Si | D34: Si | E34: Si | F34: TRUE | G34: AMEX | H34: =B34*0.9 -> 1097.1
A35: Podologia Productos | B35: 359 | C35: Si | F35: TRUE | G35: AMEX | H35: =B35*0.9 -> 323.1
A36: Vacuna Alfredo | B36: 2500 | C36: Si | D36: Si | F36: TRUE | G36: AMEX | H36: =B36*0.9 -> 2250
A37: Vacuna Lena | B37: 1700 | C37: Si | D37: Si | F37: TRUE | G37: AMEX | H37: =B37*0.9 -> 1530
A38: Medicinas ojo Lena | B38: 2291 | C38: Si | D38: Si | F38: TRUE | G38: AMEX | H38: =B38*0.9 -> 2061.9
A39: Gastos Extra HIP | B39: 2577.17 | C39: Si | F39: TRUE | G39: AMEX | H39: =B39*0.9 -> 2319.453
A40: Oftalmologa Lena | B40: 1300 | C40: Si | F40: TRUE | G40: 2Now Gastos | H40: =B40*0.9 -> 1170
A41: Pulmicort y combivent | B41: 987 | C41: SI | F41: TRUE | G41: AMEX | H41: =B41*0.9 -> 888.3
A42: Eugenio Sue | B42: 6247.51 | C42: Si | F42: TRUE | G42: HSBC World elite | H42: =B42*0.9 -> 5622.759
A43: Vacuna Alfredo | B43: 2800 | F43: TRUE | G43: AMEX | H43: =B43*0.9 -> 2520
A44: Consulta Endocrinologia | B44: 1400 | C44: SI | D44: Si | E44: Si | F44: TRUE | G44: AMEX | H44: =B44*0.9 -> 1260
A45: Adimod | B45: 2836 | C45: Si | F45: TRUE | G45: AMEX | H45: =B45*0.9 -> 2552.4
A46: Lena consulta oftalmo | B46: 1100 | F46: FALSE | G46: 2Now Gastos | H46: =B46*0.9 -> 990
A47: Lena lentes | B47: 2273.6 | F47: FALSE | G47: 2Now Gastos | H47: =B47*0.9 -> 2046.24
A48: Medicinas Alfredo | B48: 2269 | C48: Si | F48: FALSE | G48: 2Now Gastos | H48: =B48*0.9 -> 2042.1
A49: Vitamina E | B49: 712.08 | C49: Si | F49: FALSE | G49: 2Now Gastos | H49: =B49*0.9 -> 640.872
A50: Vacuna Lena | B50: 1700 | C50: Si | F50: TRUE | G50: AMEX | H50: =B50*0.9 -> 1530
A52: Vacuna Alfredo | B52: 2800 | C52: Si | F52: TRUE | G52: AMEX | H52: =B52*0.9 -> 2520
C58: Total Gastado | D58: Total por pagar | H58: =712.08+237.2+1499+2000+146+79+398 -> 5071.28
B59: AMEX | C59: =SUMIF(G2:G38,B59,B2:B58) -> 35066 | D59: =SUMIFS(B2:B56,F2:F56,false,G2:G56,B59) -> 0 | H59: =7334.12-H58 -> 2262.84
B60: 2Now Gastos | C60: =SUMIF(G2:G31,B60,B2:B58) -> 22750 | D60: =SUMIFS(B3:B56,F3:F56,false,G3:G56,B60) -> 6354.68
B61: HSBC World elite | C61: =SUMIF(G2:G56,B61,B2:B56) -> 6847.51 | D61: =SUMIFS(B4:B57,F4:F57,false,G4:G57,B61) -> 0
I62: =7334.12-2273.6 -> 5060.52
C64: =SUM(C59:C63) -> 64663.51

Sheet Gastos Medicos Mayores
A1: Concepto | B1: Monto | C1: Facturado | D1: Pagado | E1: Reembolso solicitado | F1: Reembolsado | G1: Tarjeta
A2: 4 Sesiones Terapia | B2: 4496.54 | C2: TRUE | D2: TRUE
A3: 1 Sesion Terapia | B3: 1124.13 | C3: TRUE | D3: TRUE
A6: Neumonia Leander
A7: Medicinas nebulizacion | B7: 1046.79 | C7: TRUE | D7: TRUE | E7: FALSE | F7: FALSE | G7: AMEX | H7: =B7*0.9 -> 942.111
A8: Consulta neumologa | B8: 1300 | C8: TRUE | D8: TRUE | E8: FALSE | F8: FALSE | G8: AMEX | H8: =B8*0.9 -> 1170
A9: Medicinas mantenimiento (Vannair, allegra, esteroide) | B9: 3507 | C9: TRUE | D9: TRUE | E9: FALSE | F9: FALSE | G9: 2Now Gastos | H9: =B9*0.9 -> 3156.3
A10: Medicinas Nuemologa | B10: 6263.5 | C10: TRUE | D10: TRUE | E10: FALSE | F10: FALSE | G10: AMEX | H10: =B10*0.9 -> 5637.15
A11: Consulta 2 neumologa | B11: 1300 | C11: FALSE | D11: TRUE | E11: FALSE | F11: FALSE | G11: AMEX | H11: =B11*0.9 -> 1170
A12: Medicinas 2 Neumologa | B12: 2081 | C12: TRUE | D12: TRUE | E12: FALSE | F12: FALSE | G12: AMEX | H12: =B12*0.9 -> 1872.9
A13: Medicinas 2 Neumologa | B13: 754 | C13: TRUE | D13: FALSE | E13: FALSE | F13: FALSE | G13: HSBC World elite | H13: =B13*0.9 -> 678.6
A14: Consulta 3 Neumologa | B14: 1400 | C14: FALSE | D14: FALSE | E14: FALSE | F14: FALSE | G14: AMEX | H14: =B14*0.9 -> 1260
A15: Medicinas 2 Neumologa | B15: 3802 | C15: FALSE | D15: FALSE | E15: FALSE | F15: FALSE | G15: 2Now Gastos | H15: =B15*0.9 -> 3421.8
J16: =SUM(B7:B15) -> 21454.29
A17: Inmunologia Leander
A18: Pruebas alergia Leander | B18: 4000 | C18: TRUE | D18: TRUE | E18: FALSE | F18: FALSE | G18: AMEX | H18: =B18*0.9 -> 3600
A19: Vacuna Leander | B19: 1700 | C19: TRUE | D19: TRUE | E19: FALSE | F19: FALSE | G19: AMEX | H19: =B19*0.9 -> 1530
A20: Vacuna Leander | B20: 1700 | C20: TRUE | D20: TRUE | E20: FALSE | F20: FALSE | G20: AMEX | H20: =B20*0.9 -> 1530
C36: Total Gastado | D36: Total por pagar
B37: AMEX | C37: =SUMIF(G$2:G32,B37,B$2:B32) -> 20791.29 | D37: =SUMIFS(B$2:B32,D$2:D32,false,G$2:G32,B37) -> 1400
B38: 2Now Gastos | C38: =SUMIF(G$2:G33,B38,B$2:B33) -> 7309 | D38: =SUMIFS(B$2:B33,D$2:D33,false,G$2:G33,B38) -> 3802

Sheet Totales y Transferencias
A1: Column 1 | B1: CLABE | C1: Referencia en deposito | D1: Total Mensual | E1: Total quincenal | F1: Programada | G1: 16/02/2025 | H1: 01/03/2025 | I1: 14/03/2025 | J1: 31/03/2025 | K1: 15/04/2025 | L1: 30/04/2025 | M1: 15/05/2025 | N1: 31/05/2025 | O1: 15/06/2025 | P1: 30/06/2025 | Q1: 15/07/2025 | R1: 31/07/25 | S1: 15/08/25 | T1: 31/08/25
A2: HSBC Flexible | B2: {=INDEX(Table3[CLABE], MATCH(A2, Table3[Nombre cuenta], 0))} -> 021180065930525793 | C2: {=INDEX(Table3[Codigo Referencia], MATCH(A2, Table3[Nombre cuenta], 0))} -> 0000011 | D2: =SUMIF(Actual!$I$3:$I$89, A2, Actual!$B$3:$B$89) -> 39300 | E2: =SUMIF(Actual!$I$3:$I$89, A2, Actual!$C$3:$C$89) -> 19650 | F2: TRUE | G2: TRUE | H2: TRUE | I2: TRUE | J2: TRUE | K2: TRUE | L2: TRUE | M2: TRUE | N2: FALSE | O2: FALSE | P2: TRUE | Q2: TRUE | R2: TRUE | S2: TRUE | T2: TRUE
A3: Uala | B3: {=INDEX(Table3[CLABE], MATCH(A3, Table3[Nombre cuenta], 0))} -> 138580000023894928 | C3: {=INDEX(Table3[Codigo Referencia], MATCH(A3, Table3[Nombre cuenta], 0))} -> 0000014 | D3: =SUMIF(Actual!$I$3:$I$89, A3, Actual!$B$3:$B$89) -> 32800 | E3: =SUMIF(Actual!$I$3:$I$89, A3, Actual!$C$3:$C$89) -> 16400 | F3: TRUE | G3: TRUE | H3: TRUE | I3: TRUE | J3: TRUE | K3: TRUE | L3: TRUE | M3: TRUE | N3: TRUE | O3: TRUE | P3: TRUE | Q3: TRUE | R3: TRUE | S3: TRUE | T3: TRUE
A4: Nu Cajita Hogar | B4: {=INDEX(Table3[CLABE], MATCH(A4, Table3[Nombre cuenta], 0))} -> 638180000177404193 | C4: {=INDEX(Table3[Codigo Referencia], MATCH(A4, Table3[Nombre cuenta], 0))} -> 0000016 | D4: =SUMIF(Actual!$I$3:$I$89, A4, Actual!$B$3:$B$89) -> 23200 | E4: =SUMIF(Actual!$I$3:$I$89, A4, Actual!$C$3:$C$89) -> 11600 | F4: TRUE | G4: TRUE | H4: TRUE | I4: TRUE | J4: TRUE | K4: TRUE | L4: TRUE | M4: TRUE | N4: TRUE | O4: TRUE | P4: TRUE | Q4: TRUE | R4: TRUE | S4: TRUE | T4: TRUE
A5: Nu Cajita Auto | B5: {=INDEX(Table3[CLABE], MATCH(A5, Table3[Nombre cuenta], 0))} -> 638180000177404193 | C5: {=INDEX(Table3[Codigo Referencia], MATCH(A5, Table3[Nombre cuenta], 0))} -> 0000012 | D5: =SUMIF(Actual!$I$3:$I$89, A5, Actual!$B$3:$B$89) -> 17500 | E5: =SUMIF(Actual!$I$3:$I$89, A5, Actual!$C$3:$C$89) -> 8750 | F5: FALSE | G5: TRUE | H5: TRUE | I5: TRUE | J5: TRUE | K5: TRUE | L5: TRUE | M5: TRUE | N5: TRUE | O5: TRUE | P5: TRUE | Q5: TRUE | R5: TRUE | S5: TRUE | T5: TRUE
A6: HSBC | B6: {=INDEX(Table3[CLABE], MATCH(A6, Table3[Nombre cuenta], 0))} -> 021180040690613986 | C6: {=INDEX(Table3[Codigo Referencia], MATCH(A6, Table3[Nombre cuenta], 0))} -> 0000001 | D6: =SUMIF(Actual!$I$3:$I$89, A6, Actual!$B$3:$B$89) -> 10000 | E6: =SUMIF(Actual!$I$3:$I$89, A6, Actual!$C$3:$C$89) -> 5000 | F6: FALSE | G6: TRUE | H6: TRUE | I6: TRUE | J6: TRUE | K6: TRUE | L6: TRUE | M6: TRUE | N6: FALSE | O6: FALSE | P6: FALSE | Q6: FALSE | R6: FALSE | S6: FALSE | T6: FALSE
A7: Nu Cajita Gastos | B7: {=INDEX(Table3[CLABE], MATCH(A7, Table3[Nombre cuenta], 0))} -> 638180000177404193 | C7: {=INDEX(Table3[Codigo Referencia], MATCH(A7, Table3[Nombre cuenta], 0))} -> 0000013 | D7: =SUMIF(Actual!$I$3:$I$89, A7, Actual!$B$3:$B$89) -> 9900 | E7: =SUMIF(Actual!$I$3:$I$89, A7, Actual!$C$3:$C$89) -> 4950 | F7: FALSE | G7: TRUE | H7: TRUE | I7: TRUE | J7: TRUE | K7: TRUE | L7: TRUE | M7: TRUE | N7: TRUE | O7: TRUE | P7: TRUE | Q7: TRUE | R7: TRUE | S7: TRUE | T7: TRUE
A8: Stori Inversion + | B8: {=INDEX(Table3[CLABE], MATCH(A8, Table3[Nombre cuenta], 0))} -> 646180402300057567 | C8: {=INDEX(Table3[Codigo Referencia], MATCH(A8, Table3[Nombre cuenta], 0))} -> 0000015 | D8: =SUMIF(Actual!$I$3:$I$89, A8, Actual!$B$3:$B$89) -> 4500 | E8: =SUMIF(Actual!$I$3:$I$89, A8, Actual!$C$3:$C$89) -> 2250 | F8: FALSE | G8: TRUE | H8: TRUE | I8: TRUE | J8: TRUE | K8: TRUE | L8: TRUE | M8: TRUE | N8: TRUE | O8: TRUE | P8: TRUE | Q8: TRUE | R8: TRUE | S8: TRUE | T8: TRUE
A9: Nu Dalia Debito | B9: {=INDEX(Table3[CLABE], MATCH(A9, Table3[Nombre cuenta], 0))} -> 638180010151893079 | C9: {=INDEX(Table3[Codigo Referencia], MATCH(A9, Table3[Nombre cuenta], 0))} -> 0000004 | D9: =SUMIF(Actual!$I$3:$I$89, A9, Actual!$B$3:$B$89) -> 3700 | E9: =SUMIF(Actual!$I$3:$I$89, A9, Actual!$C$3:$C$89) -> 1850 | F9: FALSE | G9: TRUE | H9: TRUE | I9: TRUE | J9: TRUE | K9: TRUE | L9: TRUE | M9: TRUE | N9: TRUE | O9: TRUE | P9: TRUE | Q9: TRUE | R9: TRUE | S9: TRUE | T9: TRUE
A10: GBM Trading | B10: {=INDEX(Table3[CLABE], MATCH(A10, Table3[Nombre cuenta], 0))} -> 601180400038253515 | C10: {=INDEX(Table3[Codigo Referencia], MATCH(A10, Table3[Nombre cuenta], 0))} -> 0000104 | D10: =SUMIF(Actual!$I$3:$I$89, A10, Actual!$B$3:$B$89) -> 500 | E10: =SUMIF(Actual!$I$3:$I$89, A10, Actual!$C$3:$C$89) -> 250 | F10: FALSE | G10: TRUE | H10: TRUE | I10: TRUE | J10: TRUE | K10: TRUE | L10: FALSE | M10: TRUE | N10: TRUE | O10: TRUE | P10: TRUE | Q10: TRUE | R10: TRUE | S10: TRUE | T10: TRUE
A11: GBM Dolares | B11: {=INDEX(Table3[CLABE], MATCH(A11, Table3[Nombre cuenta], 0))} -> 601180400049499232 | C11: {=INDEX(Table3[Codigo Referencia], MATCH(A11, Table3[Nombre cuenta], 0))} -> 0000103 | D11: =SUMIF(Actual!$I$3:$I$89, A11, Actual!$B$3:$B$89) -> 500 | E11: =SUMIF(Actual!$I$3:$I$89, A11, Actual!$C$3:$C$89) -> 250 | F11: FALSE | G11: TRUE | H11: TRUE | I11: TRUE | J11: TRUE | K11: TRUE | L11: TRUE | M11: TRUE | N11: TRUE | O11: TRUE | P11: TRUE | Q11: TRUE | R11: TRUE | S11: TRUE | T11: TRUE
C14: Total | D14: =SUM(Current_transactions[Total Mensual]) -> 141900 | E14: =SUM(Current_transactions[Total quincenal]) -> 70950 | K14: Mensual | L14: Quincenal
J15: Total | K15: =Actual!B16+Actual!B32+Actual!B40+Actual!B48+Actual!B60+Actual!B77+Actual!B85 -> 141900 | L15: =Actual!C16+Actual!C32+Actual!C40+Actual!C48+Actual!C60+Actual!C85+Actual!C77 -> 70950
D26: =D14+5000 -> 146900 | E26: =E14+5000 -> 75950 | N26: v

Sheet Actual
A1: Kids | Q1: Salario Mensual | R1: Salario Quincenal
Q2: 142000 | R2: =Q2/2 -> 71000
A3: Nombre | B3: Mensual | C3: Quincenal | D3: Es Anual | E3: Costo Anual | F3: Costo Mensual | G3: Comentarios | H3: Cuenta Cargo | I3: Cuenta deposito
A4: Colegiatura Lena | B4: =CEILING(F4,100) -> 15800 | C4: =CEILING(B4/2, 10) -> 7900 | D4: =IF(E4>0, true) -> FALSE | F4: 15770 | H4: HSBC World elite | I4: Uala | P4: Objetivos Ahorro
A5: Colegiatura Leander | B5: =CEILING(F5,100) -> 8000 | C5: =CEILING(B5/2, 10) -> 4000 | D5: =IF(E5>0, true) -> FALSE | F5: 7915 | H5: Uala | I5: Uala | P5: Largo Plazo (11%) | Q5: =Q2*0.11 -> 15620 | R5: =Q5/2 -> 7810
A6: Horario Extendido Leander | B6: =CEILING(F6,100) -> 2200 | C6: =CEILING(B6/2, 10) -> 1100 | D6: =IF(E6>0, true) -> FALSE | F6: 2200 | G6: 2 dias por semana | H6: Uala | I6: Uala | P6: Corto Plazo (9%) | Q6: =Q2*0.09 -> 12780 | R6: =Q6/2 -> 6390
A7: Clases de aleman | B7: =CEILING(F7,100) -> 2000 | C7: =CEILING(B7/2, 10) -> 1000 | D7: =IF(E7>0, true) -> FALSE | F7: 2000 | G7: 4 clases al mes (4 Mi por mes) | H7: HSBC World elite | I7: Uala
A8: Inscripcion Lena | B8: =CEILING(F8,100) -> 1700 | C8: =CEILING(B8/2, 10) -> 850 | D8: =IF(E8>0, true) -> TRUE | E8: 19500 | F8: =E8/12 -> 1625 | G8: Al menos 50% de la siguiente inscripcion | H8: HSBC World elite | I8: Stori Inversion +
A9: Natacion Lena | B9: =CEILING(F9,100) -> 1300 | C9: =CEILING(B9/2, 10) -> 650 | D9: =IF(E9>0, true) -> FALSE | F9: 1270 | G9: =Deuda!A23Vuelo -> #NAME? | H9: HSBC World elite | I9: Uala
A10: Ballet | B10: =CEILING(F10,100) -> 1200 | C10: =CEILING(B10/2, 10) -> 600 | D10: =IF(E10>0, true) -> FALSE | F10: 1200 | H10: Nu Dalia Debito | I10: Nu Dalia Debito
A11: Natacion Leander | B11: =CEILING(F11,100) -> 1300 | C11: =CEILING(B11/2, 10) -> 650 | D11: =IF(E11>0, true) -> FALSE | F11: 1270 | H11: HSBC World elite | I11: Uala
A12: Lena Yoga | B12: =CEILING(F12,100) -> 1100 | C12: =CEILING(B12/2, 10) -> 550 | D12: =IF(E12>0, true) -> FALSE | F12: =CEILING(1100, 10) -> 1100 | H12: HSBC World elite | I12: Uala
A13: Lena Robotica | B13: =CEILING(F13,100) -> 1100 | C13: =CEILING(B13/2, 10) -> 550 | D13: =IF(E13>0, true) -> FALSE | F13: 1100 | H13: HSBC World elite | I13: Uala
A14: Inscripcion Leander | B14: =CEILING(F14,100) -> 800 | C14: =CEILING(B14/2, 10) -> 400 | D14: =IF(E14>0, true) -> TRUE | E14: =9500 -> 9500 | F14: =E14/12 -> 791.66667 | H14: Uala | I14: Stori Inversion +
A16: Total | B16: =SUM(B3:B15) -> 36500 | C16: =SUM(C3:C15) -> 18250 | F16: =SUM(F3:F15) -> 36241.667 | L16: =E8+E23+E24+E26+E29+E28+E54+E55+E57+E73+E14 -> 62839
A18: Suscripciones
A20: Nombre | B20: Mensual | C20: Quincenal | D20: Es Anual | H20: Cuenta Cargo | I20: Cuenta Deposito
A21: Sports World | B21: =CEILING(F21,100) -> 3900 | C21: =CEILING(B21/2, 10) -> 1950 | D21: =IF(E21>0, true) -> FALSE | F21: 3850 | H21: HSBC World elite | I21: Nu Cajita Gastos
A22: Netflix | B22: =CEILING(F22,100) -> 400 | C22: =CEILING(B22/2, 10) -> 200 | D22: =IF(E22>0, true) -> FALSE | F22: 350 | H22: 2Now Gastos | I22: Nu Cajita Gastos
A23: NFL game pass | B23: =CEILING(F23,100) -> 300 | C23: =CEILING(B23/2, 10) -> 150 | D23: =IF(E23>0, true) -> TRUE | E23: 3300 | F23: =E23/12 -> 275 | H23: HSBC World elite | I23: Stori Inversion +
A24: Disney | B24: =CEILING(F24,100) -> 200 | C24: =CEILING(B24/2, 10) -> 100 | D24: =IF(E24>0, true) -> TRUE | E24: 2400 | F24: =E24/12 -> 200 | H24: 2Now Gastos | I24: Nu Cajita Gastos
A25: Max | B25: =CEILING(F25,100) -> 200 | C25: =CEILING(B25/2, 10) -> 100 | D25: =IF(E25>0, true) -> FALSE | F25: 199 | H25: 2Now Gastos | I25: Nu Cajita Gastos
A26: Spotify | B26: =CEILING(F26,100) -> 200 | C26: =CEILING(B26/2, 10) -> 100 | D26: =IF(E26>0, true) -> TRUE | E26: 1990 | F26: =E26/12 -> 165.83333 | H26: HSBC World elite | I26: Stori Inversion +
A27: Digital Ocean | B27: =CEILING(F27,100) -> 200 | C27: =CEILING(B27/2, 10) -> 100 | D27: =IF(E27>0, true) -> FALSE | F27: 130 | H27: HSBC World elite | I27: Nu Cajita Gastos
A28: Prime | B28: =CEILING(F28,100) -> 100 | C28: =CEILING(B28/2, 10) -> 50 | D28: =IF(E28>0, true) -> TRUE | E28: 899 | F28: =E28/12 -> 74.916667 | H28: HSBC World elite | I28: Stori Inversion +
A29: Uber one | B29: =CEILING(F29,100) -> 100 | C29: =CEILING(B29/2, 10) -> 50 | D29: =IF(E29>0, true) -> TRUE | E29: 750 | F29: =E29/12 -> 62.5 | H29: HSBC World elite | I29: Stori Inversion +
A30: Frontend masters | B30: =CEILING(F30,100) -> 0 | C30: =CEILING(B30/2, 10) -> 0 | D30: =IF(E30>0, true) -> FALSE | H30: HSBC World elite | I30: Nu Cajita Gastos
A32: Total | B32: =SUM(B21:B30) -> 5600 | C32: =SUM(C21:C30) -> 2800 | F32: =SUM(F21:F30) -> 5307.25
A34: Telecomunicaciones
A35: Nombre | B35: Mensual | C35: Quincenal | D35: Es Anual | H35: Cuenta Cargo | I35: Cuenta Deposito
A36: Totalplay (Internet + TV) | B36: =CEILING(F36,100) -> 1400 | C36: =CEILING(B36/2, 10) -> 700 | D36: =IF(E36>0, true) -> FALSE | F36: 1399 | H36: 2Now Hogar | I36: Nu Cajita Hogar
A37: Movistar Dalia | B37: =CEILING(F37,100) -> 500 | C37: =CEILING(B37/2, 10) -> 250 | D37: =IF(E37>0, true) -> FALSE | F37: 500 | H37: 2Now Gastos | I37: Nu Cajita Gastos
A38: Movistar Alfredo | B38: =CEILING(F38,100) -> 500 | C38: =CEILING(B38/2, 10) -> 250 | D38: =IF(E38>0, true) -> FALSE | F38: 439 | H38: 2Now Gastos | I38: Nu Cajita Gastos
A40: Total | B40: =SUM(B36:B39) -> 2400 | C40: =SUM(C36:C39) -> 1200 | F40: =SUM(F36:F39) -> 2338
A42: Ahorro
A43: Nombre | B43: Mensual | C43: Quincenal | D43: Es Anual | H43: Cuenta Cargo | I43: Cuenta Deposito
A44: Trading | B44: =CEILING(F44,100) -> 500 | C44: =CEILING(B44/2, 10) -> 250 | D44: =IF(E44>0, true) -> FALSE | F44: 450 | H44: HSBC | I44: GBM Trading
A45: Dolares | B45: =CEILING(F45,100) -> 500 | C45: =CEILING(B45/2, 10) -> 250 | D45: =IF(E45>0, true) -> FALSE | F45: 450 | H45: HSBC | I45: GBM Dolares
A46: Largo plazo | B46: =CEILING(F46,100) -> 1100 | C46: =CEILING(B46/2, 10) -> 550 | D46: =IF(E46>0, true) -> FALSE | F46: 1100 | H46: Stori Inversion + | I46: Stori Inversion +
A48: Total | B48: =SUM(B44:B46) -> 2100 | C48: =SUM(C44:C46) -> 1050 | F48: =SUM(F44:F46) -> 2000
A50: Auto
A51: Nombre | B51: Mensual | C51: Quincenal | D51: Es Anual | H51: Cuenta Cargo | I51: Cuenta Deposito
A52: Nuevo Auto | B52: =CEILING(F52,100) -> 11000 | C52: =CEILING(B52/2, 10) -> 5500 | D52: =IF(E52>0, true) -> FALSE | F52: 11000 | H52: HSBC | I52: Nu Cajita Auto
A53: Gasolina | B53: =CEILING(F53,100) -> 3700 | C53: =CEILING(B53/2, 10) -> 1850 | D53: =IF(E53>0, true) -> FALSE | F53: 3700 | H53: 2Now Gastos | I53: Nu Cajita Auto
A54: Seguro | B54: =CEILING(F54,100) -> 800 | C54: =CEILING(B54/2, 10) -> 400 | D54: =IF(E54>0, true) -> TRUE | E54: 9500 | F54: =E54/12 -> 791.66667 | H54: 2Now Gastos | I54: Nu Cajita Auto | X54: =#REF!+#REF!+Deuda!E5+#REF!+#REF!+#REF! -> #REF!
A55: Matenimiento | B55: =CEILING(F55,100) -> 800 | C55: =CEILING(B55/2, 10) -> 400 | D55: =IF(E55>0, true) -> TRUE | E55: 9500 | F55: =E55/12 -> 791.66667 | H55: 2Now Gastos | I55: Nu Cajita Auto
A56: Lavado | B56: =CEILING(F56,100) -> 600 | C56: =CEILING(B56/2, 10) -> 300 | D56: =IF(E56>0, true) -> FALSE | F56: 600 | H56: 2Now Gastos | I56: Nu Cajita Auto
A57: Tenencia | B57: =CEILING(F57,100) -> 400 | C57: =CEILING(B57/2, 10) -> 200 | D57: =IF(E57>0, true) -> TRUE | E57: 4000 | F57: =E57/12 -> 333.33333 | H57: 2Now Gastos | I57: Nu Cajita Auto
A58: Verificacion | B58: =CEILING(F58,100) -> 200 | C58: =CEILING(B58/2, 10) -> 100 | D58: =IF(E58>0, true) -> TRUE | E58: 1500 | F58: =E58/12 -> 125 | H58: 2Now Gastos | I58: Nu Cajita Auto
A60: Total | B60: =SUM(B52:B59) -> 17500 | C60: =SUM(C52:C59) -> 8750 | F60: =SUM(F52:F58) -> 17341.667
A62: Zuhause
A63: Nombre | B63: Mensual | C63: Quincenal | D63: Es Anual | H63: Cuenta Cargo | I63: Cuenta Deposito
A64: Renta | B64: =CEILING(F64,100) -> 37500 | C64: =CEILING(B64/2, 10) -> 18750 | D64: =IF(E64>0, true) -> FALSE | F64: 37500 | H64: HSBC | I64: HSBC Flexible
A65: Supermercado y comida | B65: =CEILING(F65,100) -> 20000 | C65: =CEILING(B65/2, 10) -> 10000 | D65: =IF(E65>0, true) -> FALSE | F65: 20000 | H65: 2Now Hogar | I65: Nu Cajita Hogar
A66: Limpieza Alicia | B66: =CEILING(F66,100) -> 3500 | C66: =CEILING(B66/2, 10) -> 1750 | D66: =IF(E66>0, true) -> FALSE | F66: =430*8 -> 3440 | G66: 430, contando 8 limpiezas al mes | H66: HSBC | I66: HSBC
A67: Limpieza Sra Dalia | B67: =CEILING(F67,100) -> 2000 | C67: =CEILING(B67/2, 10) -> 1000 | D67: =IF(E67>0, true) -> FALSE | F67: =500*4 -> 2000 | G67: 4 jueves por mes | H67: HSBC | I67: HSBC
A68: Gas | B68: =CEILING(F68,100) -> 800 | C68: =CEILING(B68/2, 10) -> 400 | D68: =IF(E68>0, true) -> FALSE | F68: =1500/2 -> 750 | G68: Recargando 1500 cada 2 meses | H68: 2Now Hogar | I68: Nu Cajita Hogar
A69: Electricidad | B69: =CEILING(F69,100) -> 700 | C69: =CEILING(B69/2, 10) -> 350 | D69: =IF(E69>0, true) -> FALSE | F69: =1250/2 -> 625 | G69: Asumiendo un gasto de 1250 al bimestre | H69: 2Now Hogar | I69: Nu Cajita Hogar
A70: Agua | B70: =CEILING(F70,100) -> 300 | C70: =CEILING(B70/2, 10) -> 150 | D70: =IF(E70>0, true) -> FALSE | F70: =(450+120)/2 -> 285 | G70: 450 Bartolache + 120 Santa Anita | H70: 2Now Hogar | I70: Nu Cajita Hogar
A71: Basura (Sr. Polo) | B71: =CEILING(F71,100) -> 300 | C71: =CEILING(B71/2, 10) -> 150 | D71: =IF(E71>0, true) -> FALSE | F71: =70*4 -> 280 | H71: HSBC | I71: HSBC
A72: Cuota Admin. Sta Anita | B72: =CEILING(F72,100) -> 1800 | C72: =CEILING(B72/2, 10) -> 900 | D72: =IF(E72>0, true) -> FALSE | F72: 1800 | H72: HSBC | I72: HSBC Flexible
A73: Predial Sta Anita | B73: =CEILING(F73,100) -> 200 | C73: =CEILING(B73/2, 10) -> 100 | D73: =IF(E73>0, true) -> TRUE | E73: 1500 | F73: =E73/12 -> 125 | H73: 2Now Hogar | I73: Stori Inversion +
A74: Hipoteca | B74: =CEILING(F74,100) -> 0 | C74: =CEILING(B74/2, 10) -> 0 | D74: =IF(E74>0, true) -> FALSE | F74: 0 | H74: HSBC | I74: HSBC
A75: ISR Renta Departamento | B75: =CEILING(F75,100) -> 200 | C75: =CEILING(B75/2, 10) -> 100 | D75: =IF(E75>0, true) -> FALSE | F75: 110 | H75: HSBC | I75: HSBC
A77: Total | B77: =SUM(B64:B76) -> 67300 | C77: =SUM(C64:C76) -> 33650 | F77: =SUM(F64:F76) -> 66915
A79: Miscelaneos
A80: Nombre | B80: Mensual | C80: Quincenal | D80: Es Anual | H80: Cuenta Cargo | I80: Cuenta Deposito
A81: Dalia mensualidad | B81: =CEILING(F81,100) -> 2500 | C81: =CEILING(B81/2, 10) -> 1250 | D81: FALSE | F81: 2500 | H81: Nu Dalia Debito | I81: Nu Dalia Debito
A82: Libre | B82: =CEILING(F82,100) -> 4000 | C82: =CEILING(B82/2, 10) -> 2000 | D82: FALSE | F82: 4000 | H82: 2Now Gastos | I82: Nu Cajita Gastos
A83: Efectivo | B83: =CEILING(F83,100) -> 4000 | C83: =CEILING(B83/2, 10) -> 2000 | D83: FALSE | F83: 4000 | H83: HSBC | I83: HSBC
A85: Total | B85: =SUM(B81:B84) -> 10500 | C85: =SUM(C81:C84) -> 5250 | F85: =SUM(F81:F84) -> 10500

Sheet Gastos Viaje Texas Dec 25
A1: WORLD ELITE
A2: Hugo Boss San Marcos | B2: 2093.93
A3: BROOKSHIRE BROS 626 | B3: 486.98
A4: Adidas AMERICA, INC. | B4: 2804.14
A5: ROSS STORES #548 | B5: 4659.13
A6: WM SUPERCENTER #6929 | B6: 2005.46
A7: MARSHALLS #819 | B7: 6461
A8: NikePOS_US | B8: 1266.04
A9: BUC-EE'S #0035 | B9: 778.95
B12: =SUM(B2:B11) -> 20555.63
A14: AMERICAN EXPRESS
A15: Tablet Amazon | B15: 2692.35
A16: Amazon US | B16: 365.97
A17: Amazon US | B17: 600.27
A18: Pizzeria | B18: 3560.57
A19: Paradies | B19: 311.23
A20: Freezing Pont | B20: 392.97
A21: Old fashiond soda | B21: 361.7
A22: Santas wonderland | B22: 369.27
A23: Blitzend parking | B23: 391.8
A24: Chevron | B24: 59.66
A25: Chevron | B25: 51.56
A26: CHISHOLM TRAIL CHUCKWAG | B26: 296.89
... A34: CROCS | B34: 2248.98
A35: Shake shack | B35: =1092.03+257.98 -> 1350.01
A36: SUNOCO | B36: 161.07
A37: Sunoco | B37: 454.17
A38: Paradies | B38: 73.36
A39: PS store * | B39: 255.77
A40: Digital Ocean * | B40: 110.92
B45: =SUM(B14:B40) -> 18942.52

Sheet Until 31.12.2024
A1: 39 | J1: Mensual | K1: Quincenal
A2: Nombre | B2: Mensual | C2: Quincenal | D2: Es Anual | E2: Cuenta Cargo | F2: Cuenta Deposito | I2: Total | J2: =B15+B30+B39+B47+B59+B75+B82 -> 139664.5 | K2: =C15+C30+C39+C47+C59+C82+C75 -> 69832.25
A3: Colegiatura Lena | B3: 15770 | C3: =B3/2 -> 7885 | D3: FALSE | E3: HSBC World elite | F3: Uala
A4: Colegiatura Leander | B4: 7915 | C4: =B4/2 -> 3957.5 | D4: FALSE | E4: HSBC | F4: Uala
A5: Futbol | B5: =1300+(1300*0.9) -> 2470 | C5: =B5/2 -> 1235 | D5: FALSE | E5: HSBC World elite | F5: Nu Cajita Gastos
A6: Lena Robotica | B6: 1100 | C6: =B6/2 -> 550 | D6: FALSE | E6: HSBC World elite | F6: Uala | G6: =B3+B6+B7+B10+B11 -> 20245
A7: Lena Yoga | B7: 1100 | C7: =B7/2 -> 550 | D7: FALSE | E7: HSBC World elite | F7: Uala
A8: Horario Extendido Leander | B8: 2200 | C8: =B8/2 -> 1100 | D8: FALSE | E8: HSBC | F8: Uala
A9: Ballet | B9: 1200 | C9: =B9/2 -> 600 | D9: FALSE | E9: Nu Dalia Debito | F9: Nu Dalia Debito
A10: Natacion Lena | B10: 1180 | C10: =B10/2 -> 590 | D10: FALSE | E10: HSBC World elite | F10: Uala
A11: Natacion Leander | B11: 1095 | C11: =B11/2 -> 547.5 | D11: FALSE | E11: HSBC World elite | F11: Uala
A12: Inscripcion Lena | B12: =15000/12 -> 1250 | C12: =B12/2 -> 625 | D12: TRUE | E12: HSBC | F12: Stori +
A13: Inscripcion Leander | B13: 750 | C13: =B13/2 -> 375 | D13: TRUE | E13: HSBC | F13: Stori + | M13: 45550 | N13: 45565 | O13: 45580 | P13: 45596 | Q13: 45611 | R13: 45626 | S13: 15 Dic 24 | T13: 31 Dic 24
I14: Total Mensual | J14: Total quincenal | K14: Programada
A15: Total | B15: =SUM(B2:B14) -> 36030 | C15: =SUM(C2:C14) -> 18015 | H15: Cetes | I15: =CEILING(SUMIF($F$2:$F$86, H15, $B$2:$B$86),100) -> 8000 | J15: =CEILING(SUMIF($F$2:$F$86, H15, $C$2:$C$86),100) -> 4000 | K15: Si (Portal Cetes) | M15: TRUE | N15: TRUE | O15: TRUE | P15: TRUE | Q15: TRUE | R15: TRUE | S15: TRUE | T15: TRUE
H16: GBM Trading | I16: =CEILING(SUMIF($F$2:$F$86, H16, $B$2:$B$86),100) -> 600 | J16: =CEILING(SUMIF($F$2:$F$86, H16, $C$2:$C$86),100) -> 300 | K16: No | M16: TRUE | N16: TRUE | O16: TRUE | P16: TRUE | Q16: TRUE | R16: TRUE | S16: TRUE | T16: FALSE
A17: Suscripciones | H17: GBM Dolares | I17: =CEILING(SUMIF($F$2:$F$86, H17, $B$2:$B$86),100) -> 600 | J17: =CEILING(SUMIF($F$2:$F$86, H17, $C$2:$C$86),100) -> 300 | K17: No | M17: TRUE | N17: TRUE | O17: TRUE | P17: TRUE | Q17: TRUE | R17: TRUE | S17: TRUE | T17: FALSE
A18: Nombre | B18: Mensual | C18: Quincenal | H18: HSBC | I18: =CEILING(SUMIF($F$2:$F$86, H18, $B$2:$B$86),100) -> 10800 | J18: =CEILING(SUMIF($F$2:$F$86, H18, $C$2:$C$86),100) -> 5400 | K18: No | M18: FALSE | N18: FALSE | O18: FALSE | P18: FALSE | Q18: FALSE | R18: FALSE | S18: FALSE | T18: FALSE
A19: Sports World | B19: 3600 | C19: =B19/2 -> 1800 | D19: FALSE | E19: HSBC World elite | F19: Nu Cajita Gastos | H19: HSBC Flexible | I19: =CEILING(SUMIF($F$2:$F$86, H19, $B$2:$B$86),100) -> 37500 | J19: =CEILING(SUMIF($F$2:$F$86, H19, $C$2:$C$86),100) -> 18800 | K19: No | M19: TRUE | N19: TRUE | O19: TRUE | P19: TRUE | Q19: FALSE | R19: TRUE | S19: TRUE | T19: TRUE
A20: Netflix | B20: =CEILING(299,10) -> 300 | C20: =B20/2 -> 150 | D20: FALSE | E20: HSBC World elite | F20: Nu Cajita Gastos | H20: Nu Cajita Auto | I20: =CEILING(SUMIF($F$2:$F$86, H20, $B$2:$B$86),100) -> 16300 | J20: =CEILING(SUMIF($F$2:$F$86, H20, $C$2:$C$86),100) -> 8200 | K20: No | M20: TRUE | N20: TRUE | O20: TRUE | P20: TRUE | Q20: TRUE | R20: TRUE | S20: TRUE | T20: TRUE
A21: Disney | B21: 299 | C21: =B21/2 -> 149.5 | D21: FALSE | E21: HSBC World elite | F21: Nu Cajita Gastos | H21: Nu Cajita Gastos | I21: =CEILING(SUMIF($F$2:$F$86, H21, $B$2:$B$86),100) -> 27600 | J21: =CEILING(SUMIF($F$2:$F$86, H21, $C$2:$C$86),100) -> 13800 | K21: No | M21: TRUE | N21: TRUE | O21: FALSE | P21: TRUE | Q21: TRUE | R21: TRUE | S21: TRUE | T21: FALSE
A22: NFL game pass | B22: =CEILING(3000/12, 10) -> 250 | C22: =B22/2 -> 125 | D22: TRUE | E22: HSBC Air | F22: Stori + | H22: Nu Dalia Debito | I22: =CEILING(SUMIF($F$2:$F$86, H22, $B$2:$B$86),100) -> 3900 | J22: =CEILING(SUMIF($F$2:$F$86, H22, $C$2:$C$86),100) -> 2000 | K22: No | M22: TRUE | N22: TRUE | O22: TRUE | P22: TRUE | Q22: TRUE | R22: TRUE | S22: TRUE | T22: TRUE
A23: Spotify | B23: 200 | C23: =B23/2 -> 100 | D23: TRUE | E23: HSBC Air | F23: Stori + | H23: Santander | I23: =CEILING(SUMIF($F$2:$F$86, H23, $B$2:$B$86),100) -> 0 | J23: =CEILING(SUMIF($F$2:$F$86, H23, $C$2:$C$86),100) -> 0 | K23: No | M23: TRUE | N23: TRUE | O23: TRUE | P23: TRUE | Q23: TRUE | R23: TRUE | S23: TRUE | T23: TRUE
A24: HBO | B24: =CEILING(199,10) -> 200 | C24: =B24/2 -> 100 | D24: FALSE | E24: HSBC World elite | F24: Nu Cajita Gastos | H24: Stori + | I24: =CEILING(SUMIF($F$2:$F$86, H24, $B$2:$B$86),100) -> 4100 | J24: =CEILING(SUMIF($F$2:$F$86, H24, $C$2:$C$86),100) -> 2100 | K24: No | M24: TRUE | N24: TRUE | O24: TRUE | P24: TRUE | Q24: TRUE | R24: TRUE | S24: TRUE | T24: TRUE
A25: Digital Ocean | B25: =IFERROR(__xludf.DUMMYFUNCTION("CEILING(GOOGLEFINANCE(""CURRENCY:USDMXN"")*6, 10)"),110.0) -> 110 | C25: =B25/2 -> 55 | D25: FALSE | E25: HSBC World elite | F25: Nu Cajita Gastos | H25: Uala | I25: =CEILING(SUMIF($F$2:$F$86, H25, $B$2:$B$86),100) -> 30400 | J25: =CEILING(SUMIF($F$2:$F$86, H25, $C$2:$C$86),100) -> 15200 | M25: TRUE | N25: TRUE | O25: TRUE | P25: TRUE | Q25: TRUE | R25: TRUE | S25: TRUE | T25: TRUE
A26: Prime | B26: =CEILING(899/12, 10) -> 80 | C26: =B26/2 -> 40 | D26: TRUE | E26: HSBC Air | F26: Stori +
A27: Uber one | B27: 70 | C27: =B27/2 -> 35 | D27: TRUE | E27: HSBC Air | F27: Stori + | I27: =SUM(I15:I25) -> 139800 | J27: =SUM(J15:J25) -> 70100
A28: Frontend masters | B28: 0 | C28: =B28/2 -> 0 | D28: FALSE | E28: HSBC World elite | F28: Nu Cajita Gastos
A30: Total | B30: =SUM(B19:B28) -> 5109 | C30: =SUM(C19:C28) -> 2554.5
A33: Telecomunicaciones | L33: =J25+J15 -> 19200
A34: Nombre | B34: Mensual | C34: Quincenal
A35: Totalplay (Internet + TV) | B35: 1200 | C35: =B35/2 -> 600 | D35: FALSE | E35: HSBC World elite | F35: Nu Cajita Gastos
A36: Movistar Dalia | B36: 500 | C36: =B36/2 -> 250 | D36: FALSE | E36: HSBC World elite | F36: Nu Cajita Gastos
A37: Movistar Alfredo | B37: 450 | C37: =B37/2 -> 225 | D37: FALSE | E37: HSBC World elite | F37: Nu Cajita Gastos
A39: Total | B39: =SUM(B35:B38) -> 2150 | C39: =SUM(C35:C38) -> 1075
L40: ¡
A41: Ahorro
A42: Nombre | B42: Mensual | C42: Quincenal
A43: Largo plazo | B43: 8000 | C43: =B43/2 -> 4000 | D43: FALSE | E43: HSBC | F43: Cetes
A44: Trading | B44: 600 | C44: =B44/2 -> 300 | D44: FALSE | E44: HSBC | F44: GBM Trading | H44: HSBC World elite | I44: =CEILING(SUMIF($E$2:$E$86, H44, $B$2:$B$86),100) -> 45800 | J44: =CEILING(SUMIF($E$2:$E$86, H44, $C$2:$C$86),100) -> 22900
A45: Dolares | B45: 600 | C45: =B45/2 -> 300 | D45: FALSE | E45: HSBC | F45: GBM Dolares | H45: HSBC Air | I45: =CEILING(SUMIF($E$2:$E$86, H45, $B$2:$B$86),100) -> 4900 | J45: =CEILING(SUMIF($E$2:$E$86, H45, $C$2:$C$86),100) -> 2500
H46: HSBC | I46: =CEILING(SUMIF($E$2:$E$86, H46, $B$2:$B$86),100) -> 85100 | J46: =CEILING(SUMIF($E$2:$E$86, H46, $C$2:$C$86),100) -> 42600
A47: Total | B47: =SUM(B43:B45) -> 9200 | C47: =SUM(C43:C45) -> 4600 | H47: Nu Dalia Debito | I47: =CEILING(SUMIF($E$2:$E$86, H47, $B$2:$B$86),100) -> 1200 | J47: =CEILING(SUMIF($E$2:$E$86, H47, $C$2:$C$86),100) -> 600
N48: Mensualidades
A49: Auto | I49: =SUM(I44:I47) -> 137000 | J49: =SUM(J44:J47) -> 68600 | N49: Concepto | O49: Cantidad | P49: # Mensualidades | Q49: Mensualidads Pagadas | R49: Mensualidad | S49: Restante | T49: Tarjeta
A50: Nombre | B50: Mensual | C50: Quincenal | N50: Bicicleta | O50: 18153.17 | P50: 12 | Q50: 8 | R50: =O50/P50 -> 1512.7642 | S50: =O50-(Q50*R50) -> 6051.0567 | T50: Air
A51: Nuevo Auto | B51: 12000 | C51: =B51/2 -> 6000 | D51: FALSE | E51: HSBC | F51: Nu Cajita Auto | N51: Entrenamiento | O51: 5677 | P51: 3 | Q51: 3 | R51: =O51/P51 -> 1892.3333 | S51: =O51-(Q51*R51) -> 0 | T51: Air
A52: Gasolina | B52: 3000 | C52: =B52/2 -> 1500 | D52: FALSE | E52: HSBC Air | F52: Nu Cajita Auto | N52: Uniformes | O52: 3600 | P52: 3 | Q52: 3 | R52: =O52/P52 -> 1200 | S52: =O52-(Q52*R52) -> 0 | T52: Air
A53: Seguro | B53: 1000 | C53: =B53/2 -> 500 | D53: TRUE | E53: HSBC Air | F53: Stori + | N53: Libros Lena | O53: 6693 | P53: 3 | Q53: 3 | R53: =O53/P53 -> 2231 | S53: =O53-(Q53*R53) -> 0 | T53: Air
A54: Matenimiento | B54: 750 | C54: =B54/2 -> 375 | D54: FALSE | E54: HSBC | F54: Nu Cajita Auto | N54: Disney on Ice | O54: 4755 | P54: 3 | Q54: 3 | R54: =O54/P54 -> 1585 | S54: =O54-(Q54*R54) -> 0 | T54: Air
A55: Lavado | B55: 400 | C55: =B55/2 -> 200 | D55: FALSE | E55: HSBC | F55: Nu Cajita Auto | N55: Hotel Cancun | O55: 53089 | P55: 12 | Q55: 6 | R55: =O55/P55 -> 4424.0833 | S55: =O55-(Q55*R55) -> 26544.5 | T55: World Elite
A56: Tenencia | B56: 300 | C56: =B56/2 -> 150 | D56: TRUE | E56: HSBC Air | F56: Stori + | N56: Vuelo Cancun | O56: 15865 | P56: 12 | Q56: 3 | R56: =O56/P56 -> 1322.0833 | S56: =O56-(Q56*R56) -> 11898.75 | T56: Invex
A57: Verificacion | B57: =CEILING((750*2)/12, 10) -> 130 | C57: =B57/2 -> 65 | D57: FALSE | E57: HSBC | F57: Nu Cajita Auto | N57: IKEA | O57: 5287 | P57: 3 | Q57: 2 | R57: =O57/P57 -> 1762.3333 | S57: =O57-(Q57*R57) -> 1762.3333 | T57: Air
N58: H&M | O58: 3640 | P58: 3 | Q58: 3 | R58: =O58/P58 -> 1213.3333 | S58: =O58-(Q58*R58) -> 0 | T58: Air
A59: Total | B59: =SUM(B51:B58) -> 17580 | C59: =SUM(C51:C58) -> 8790 | N59: Monster Jam | O59: 3683 | P59: 5 | Q59: 3 | R59: =O59/P59 -> 736.6 | S59: =O59-(Q59*R59) -> 1473.2 | T59: Air
N60: Mecanico | O60: 4060 | P60: 3 | Q60: 3 | R60: =O60/P60 -> 1353.3333 | S60: =O60-(Q60*R60) -> 0 | T60: Air
A61: Zuhause | N61: H&M 2 | O61: 3572 | P61: 3 | Q61: 2 | R61: =O61/P61 -> 1190.6667 | S61: =O61-(Q61*R61) -> 1190.6667 | T61: Air
A62: Nombre | B62: Mensual | C62: Quincenal | N62: teléfono | O62: 21154.38 | P62: 6 | Q62: 2 | R62: =O62/P62 -> 3525.73 | S62: =O62-(Q62*R62) -> 14102.92 | T62: World Elite
A63: Renta | B63: 37500 | C63: =B63/2 -> 18750 | D63: FALSE | E63: HSBC | F63: HSBC Flexible | N63: Muebles de patio | O63: 13498 | P63: 12 | Q63: 0 | R63: =O63/P63 -> 1124.8333 | S63: =O63-(Q63*R63) -> 13498 | T63: World Elite
A64: Supermercado | B64: =13200-B80 -> 7640 | C64: =B64/2 -> 3820 | D64: FALSE | E64: HSBC World elite | F64: Nu Cajita Gastos | H64: Efectivo quincenal | I64: =C80+C65 -> 4500
A65: Limpieza Alicia | B65: =(430*8) -> 3440 | C65: =B65/2 -> 1720 | D65: FALSE | E65: HSBC | F65: HSBC
A66: Limpieza Sra Dalia | B66: =500*4 -> 2000 | C66: =B66/2 -> 1000 | D66: FALSE | E66: HSBC | F66: Nu Cajita Gastos
A67: Electricidad | B67: 650 | C67: =B67/2 -> 325 | D67: FALSE | E67: HSBC World elite | F67: Nu Cajita Gastos
A68: Gas | B68: 750 | C68: =B68/2 -> 375 | D68: FALSE | E68: HSBC World elite | F68: Nu Cajita Gastos
A69: Agua | B69: =(600+111)/2 -> 355.5 | C69: =B69/2 -> 177.75 | D69: FALSE | E69: HSBC World elite | F69: Nu Cajita Gastos | K69: =47841-B3-B6-B7-B10-B11 -> 27596
A70: Sta Anita | O70: =SUM(O50:O61) -> 128074.17 | S70: =SUM(S50:S64) -> 76521.427
A71: Hipoteca | C71: =B71/2 -> 0 | D71: FALSE | E71: HSBC | F71: Santander
A72: Mantenimiento | B72: 1800 | C72: =B72/2 -> 900 | D72: FALSE | E72: HSBC | F72: HSBC
A73: Predial | B73: 200 | C73: =B73/2 -> 100 | D73: TRUE | E73: HSBC | F73: Stori + | N73: =70054.59-16036.05-720-44240.83 -> 9057.71 | S73: =S50+S57+S58+S59+S61 -> 10477.257 | T73: Restante Air
N74: =N73-1200 -> 7857.71
A75: Total | B75: =SUM(B63:B74) -> 54335.5 | C75: =SUM(C63:C74) -> 27167.75 | S75: =S62+S55+S63 -> 54145.42 | T75: Restante World Elite
S76: =S56 -> 11898.75 | T76: Restante Invex
A77: Miscelaneos
A78: Libre | B78: 7000 | C78: =B78/2 -> 3500 | D78: FALSE | E78: HSBC World elite | F78: Nu Cajita Gastos
A79: Dalia mensualidad | B79: 2700 | C79: =B79/2 -> 1350 | D79: FALSE | E79: Nu Dalia | F79: Nu Dalia Debito
A80: Efectivo | B80: 5560 | C80: =B80/2 -> 2780 | D80: FALSE | E80: HSBC | F80: HSBC
A82: Total | B82: =SUM(B78:B81) -> 15260 | C82: =SUM(C78:C81) -> 7630

Sheet Until 15.05.2024
A1: Kinder | J1: Mensual | K1: Quincenal
A2: Nombre | B2: Mensual | C2: Quincenal | D2: Es Anual | I2: Total | J2: =B13+B28+B36+B44+B55+B69+B77 -> 132405 | K2: =C13+C28+C36+C44+C55+C77+C69 -> 66202.5
A3: Inscripcion Leander | B3: =CEILING((7500)/12, 100) -> 700 | C3: =B3/2 -> 350 | D3: TRUE | E3: Klar
A4: Inscripcion Lena | B4: =CEILING((9500)/12, 100) -> 800 | C4: =B4/2 -> 400 | D4: TRUE | E4: Klar
A5: Ballet | B5: 1200 | C5: =B5/2 -> 600 | D5: FALSE | E5: Nu Dalia
A6: Colegiatura Leander | B6: =CEILING(7124,100) -> 7200 | C6: =B6/2 -> 3600 | D6: FALSE | E6: HSBC Ahorro
A7: Colegiatura Lena | B7: =CEILING(7520, 100) -> 7600 | C7: =B7/2 -> 3800 | D7: FALSE | E7: HSBC Ahorro
A8: Horario Extendido Lena | B8: 2200 | C8: =B8/2 -> 1100 | D8: FALSE | E8: HSBC Ahorro
A9: Horario Extendido Leander | B9: 2200 | C9: =B9/2 -> 1100 | D9: FALSE | E9: HSBC Ahorro
A10: Natacion Leander | B10: 1095 | C10: =B10/2 -> 547.5 | D10: FALSE | E10: HSBC Ahorro
A11: Natacion Lena | B11: 1180 | C11: =B11/2 -> 590 | D11: FALSE | E11: HSBC Ahorro
I12: Total Mensual | J12: Total quincenal | K12: Programada
A13: Total | B13: =SUM(B2:B12) -> 24175 | C13: =SUM(C2:C12) -> 12087.5 | H13: Nu Dalia | I13: =CEILING(SUMIF($E$2:$E$80, H13, $B$2:$B$80),100) -> 3200 | J13: =CEILING(SUMIF($E$2:$E$80, H13, $C$2:$C$80),100) -> 1600 | K13: SI
H14: HSBC Ahorro | I14: =CEILING(SUMIF($E$2:$E$80, H14, $B$2:$B$80),100) -> 59000 | J14: =CEILING(SUMIF($E$2:$E$80, H14, $C$2:$C$80),100) -> 29500 | K14: Si
A15: Suscripciones | H15: Nu | I15: =CEILING(SUMIF($E$2:$E$80, H15, $B$2:$B$80),100) -> 17800 | J15: =CEILING(SUMIF($E$2:$E$80, H15, $C$2:$C$80),100) -> 8900 | K15: Si
A16: Nombre | B16: Mensual | C16: Quincenal | H16: Klar | I16: =CEILING(SUMIF($E$2:$E$80, H16, $B$2:$B$80),100) -> 3100 | J16: =CEILING(SUMIF($E$2:$E$80, H16, $C$2:$C$80),100) -> 1600 | K16: Si (hacia NU)
A17: Prime | B17: =CEILING(899/12, 10) -> 80 | C17: =B17/2 -> 40 | D17: TRUE | E17: Klar | H17: Cetes | I17: =CEILING(SUMIF($E$2:$E$80, H17, $B$2:$B$80),100) -> 6000 | J17: =CEILING(SUMIF($E$2:$E$80, H17, $C$2:$C$80),100) -> 3000 | K17: Si (Portal Cetes)
A18: NFL game pass | B18: =CEILING(2500/12, 10) -> 210 | C18: =B18/2 -> 105 | D18: TRUE | E18: Klar | H18: GBM | I18: =CEILING(SUMIF($E$2:$E$80, H18, $B$2:$B$80),100) -> 2000 | J18: =CEILING(SUMIF($E$2:$E$80, H18, $C$2:$C$80),100) -> 1000 | K18: Si
A19: Digital Ocean | B19: =IFERROR(__xludf.DUMMYFUNCTION("CEILING(GOOGLEFINANCE(""CURRENCY:USDMXN"")*6, 10)"),110.0) -> 110 | C19: =B19/2 -> 55 | D19: FALSE | E19: Stori + | H19: Santander | I19: =CEILING(SUMIF($E$2:$E$80, H19, $B$2:$B$80),100) -> 14800 | J19: =CEILING(SUMIF($E$2:$E$80, H19, $C$2:$C$80),100) -> 7400 | K19: Si
A20: Paramount | B20: =CEILING(109,10) -> 110 | C20: =B20/2 -> 55 | D20: FALSE | E20: Stori + | H20: Stori + | I20: =CEILING(SUMIF($E$2:$E$80, H20, $B$2:$B$80),100) -> 4800 | J20: =CEILING(SUMIF($E$2:$E$80, H20, $C$2:$C$80),100) -> 2400 | K20: Si
A21: HBO | B21: =CEILING(399/3,10) -> 140 | C21: =B21/2 -> 70 | D21: FALSE | E21: Stori + | H21: HSBC | I21: =CEILING(SUMIF($E$2:$E$80, H21, $B$2:$B$80),100) -> 20100 | J21: =CEILING(SUMIF($E$2:$E$80, H21, $C$2:$C$80),100) -> 10100
A22: Disney | B22: =CEILING(249,10) -> 250 | C22: =B22/2 -> 125 | D22: FALSE | E22: Stori + | H22: BBVA | I22: =CEILING(SUMIF($E$2:$E$80, H22, $B$2:$B$80),100) -> 1800 | J22: =CEILING(SUMIF($E$2:$E$80, H22, $C$2:$C$80),100) -> 900 | K22: Si
A23: Netflix | B23: =CEILING(299,10) -> 300 | C23: =B23/2 -> 150 | D23: FALSE | E23: Stori +
A24: Frontend masters | B24: =IFERROR(__xludf.DUMMYFUNCTION("CEILING(GOOGLEFINANCE(""CURRENCY:USDMXN"")*39, 10)"),680.0) -> 680 | C24: =B24/2 -> 340 | D24: FALSE | E24: Stori +
A25: Uber one | B25: 70 | C25: =B25/2 -> 35 | D25: FALSE | E25: Stori +
A26: Spotify | B26: 200 | C26: =B26/2 -> 100 | D26: FALSE | E26: Stori + | J26: =SUM(J13:J22) -> 66400
A28: Total | B28: =SUM(B17:B27) -> 2150 | C28: =SUM(C17:C27) -> 1075
A30: Telecomunicaciones
A31: Nombre | B31: Mensual | C31: Quincenal
A32: Movistar Dalia | B32: 500 | C32: =B32/2 -> 250 | D32: FALSE | E32: Stori +
A33: Movistar Alfredo | B33: 600 | C33: =B33/2 -> 300 | D33: FALSE | E33: Stori +
A34: Totalplay (Internet + TV) | B34: 1200 | C34: =B34/2 -> 600 | D34: FALSE | E34: Stori +
A36: Total | B36: =SUM(B32:B35) -> 2300 | C36: =SUM(C32:C35) -> 1150
A38: Ahorro
A39: Nombre | B39: Mensual | C39: Quincenal
A40: Personal | B40: 2000 | C40: =B40/2 -> 1000 | D40: FALSE | E40: GBM
A41: Largo plazo | B41: 6000 | C41: =B41/2 -> 3000 | D41: FALSE | E41: Cetes
A42: Nuevo Auto | B42: 9000 | C42: =B42/2 -> 4500 | D42: FALSE | E42: Nu
A44: Total | B44: =SUM(B40:B43) -> 17000 | C44: =SUM(C40:C43) -> 8500
A46: Auto
A47: Nombre | B47: Mensual | C47: Quincenal
A48: Verificacion | B48: =CEILING((700*2)/12, 10) -> 120 | C48: =B48/2 -> 60 | D48: FALSE | E48: Nu
A49: Tenencia | B49: =CEILING(2500/12, 10) -> 210 | C49: =B49/2 -> 105 | D49: TRUE | E49: Klar
A50: Lavado | B50: 600 | C50: =B50/2 -> 300 | D50: FALSE | E50: HSBC
A51: Seguro | B51: =CEILING(10000/12, 100) -> 900 | C51: =B51/2 -> 450 | D51: TRUE | E51: Klar
A52: Matenimiento | B52: 1500 | C52: =B52/2 -> 750 | D52: FALSE | E52: Nu
A53: Gasolina | B53: 3500 | C53: =B53/2 -> 1750 | D53: FALSE | E53: Nu
A55: Total | B55: =SUM(B48:B54) -> 6830 | C55: =SUM(C48:C54) -> 3415
A57: Zuhause
A58: Nombre | B58: Mensual | C58: Quincenal
A59: Electricidad | B59: 600 | C59: =B59/2 -> 300 | D59: FALSE | E59: Stori +
A60: Gas | B60: 650 | C60: =B60/2 -> 325 | D60: FALSE | E60: HSBC
A61: Supermercado | B61: 12300 | C61: =B61/2 -> 6150 | D61: FALSE | E61: HSBC
A62: Limpieza | B62: =400*12 -> 4800 | C62: =B62/2 -> 2400 | D62: FALSE | E62: Santander
A63: Renta | B63: 37500 | C63: =B63/2 -> 18750 | D63: FALSE | E63: HSBC Ahorro
A64: Sta Anita
A65: Predial | B65: 200 | C65: =B65/2 -> 100 | D65: TRUE | E65: Klar
A66: Mantenimiento | B66: 1800 | C66: =B66/2 -> 900 | D66: FALSE | E66: BBVA
A67: Hipoteca | B67: 6000 | C67: =B67/2 -> 3000 | D67: FALSE | E67: Santander
A69: Total | B69: =SUM(B59:B68) -> 63850 | C69: =SUM(C59:C68) -> 31925
A71: Miscelaneos
A72: Dalia mensualidad | B72: 2000 | C72: =B72/2 -> 1000 | D72: FALSE | E72: Nu Dalia
A73: Efectivo | B73: 4000 | C73: =B73/2 -> 2000 | D73: FALSE | E73: Santander
A74: Libre | B74: 6500 | C74: =B74/2 -> 3250 | D74: FALSE | E74: HSBC
A75: Sports World | B75: 3600 | C75: =B75/2 -> 1800 | D75: FALSE | E75: Nu
A77: Total | B77: =SUM(B72:B75) -> 16100 | C77: =SUM(C72:C75) -> 8050

Sheet Until 31.07.23
A1: Subscripciones | B1: Mensual | C1: Quincenal | F1: Seguros, mantenimiento, sin categoría | G1: Mensual | H1: Quincenal
A2: Netflix | B2: 299 | C2: =B2/2 -> 149.5 | D2: Nu | F2: Seguro auto | G2: =10000/12 -> 833.33333 | H2: =G2/2 -> 416.66667 | I2: Finamex | M2: Bancos y conceptos
A3: Prime | B3: =899/12 -> 74.916667 | C3: =B3/2 -> 37.458333 | D3: Finamex | F3: Mtto. edificio | G3: 1600 | H3: =G3/2 -> 800 | I3: BBVA | M3: Santander
A4: Apple | B4: 99 | C4: =B4/2 -> 49.5 | D4: Nu | F4: Bodega | G4: 2449.9 | H4: =G4/2 -> 1224.95 | I4: Nu | M4: Nu
A5: HBO | B5: =399/3 -> 133 | C5: =B5/2 -> 66.5 | D5: Nu | F5: Limpieza | G5: =400*12 -> 4800 | H5: =G5/2 -> 2400 | I5: Efectivo | M5: GBM
A6: Disney | B6: 249 | C6: =B6/2 -> 124.5 | D6: Nu | F6: Pago adelantado hipoteca | G6: 32500 | H6: =G6/2 -> 16250 | I6: Santander | M6: Finamex
A7: Digital Ocean | B7: =IFERROR(__xludf.DUMMYFUNCTION("GOOGLEFINANCE(""CURRENCY:USDMXN"")*6"),103.30260000000001) -> 103.3026 | C7: =B7/2 -> 51.6513 | D7: Nu | F7: Dalia mensualidad | G7: 2000 | H7: =G7/2 -> 1000 | I7: BBVA | M7: BBVA
A8: Frontend masters | B8: =IFERROR(__xludf.DUMMYFUNCTION("GOOGLEFINANCE(""CURRENCY:USDMXN"")*39"),671.4669000000001) -> 671.4669 | C8: =B8/2 -> 335.73345 | D8: Nu | F8: Inscripcion niños | G8: =(7500+3500)/12 -> 916.66667 | H8: =G8/2 -> 458.33333 | I8: Finamex | M8: Cetes
A9: NFL game pass | B9: =2500/12 -> 208.33333 | C9: =B9/2 -> 104.16667 | D9: Nu | F9: Lavado auto | G9: 600 | H9: =G9/2 -> 300 | I9: Efectivo | M9: Efectivo
A11: Subtotal | B11: =SUM(B2:B10) -> 1838.0195 | C11: =SUM(C2:C10) -> 919.00975 | F11: Subtotal | G11: =SUM(G2:G10) -> 45699.9 | H11: =SUM(H2:H10) -> 22849.95
A12: Total | B12: =CEILING(SUM(B2:B10), 100) -> 1900 | C12: =CEILING(SUM(C2:C10), 100) -> 1000 | F12: Total | G12: =CEILING(SUM(G2:G10), 100) -> 45700 | H12: =CEILING(SUM(H2:H10), 100) -> 22900 | K12: Salario Mensual | L12: =L13*2 -> 130000
K13: Salario quincenal | L13: 65000
A16: Servicios e impuestos | F16: Fijos | K16: Total gastos mensual | L16: =B12+G12+B28+G28 -> 118200
A17: Predial | B17: =530/12 -> 44.166667 | C17: =B17/2 -> 22.083333 | D17: Finamex | F17: Hipoteca | G17: 13500 | H17: =G17/2 -> 6750 | I17: Santander | K17: Total gastos quincenal | L17: =L16/2 -> 59100
A18: Tenencia | B18: =2500/12 -> 208.33333 | C18: =B18/2 -> 104.16667 | D18: Finamex | F18: Colegiatura Lena | G18: =7520+1600+600 -> 9720 | H18: =G18/2 -> 4860 | I18: Santander
A19: Verificacion | B19: =(600*2)/12 -> 100 | C19: =B19/2 -> 50 | D19: GBM | F19: Colegiatura Leander | G19: =7124+(1600+600) -> 9324 | H19: =G19/2 -> 4662 | I19: Santander | K19: DISPONIBLE QUINCENAL | L19: =L13-L17 -> 5900
A20: Gas | B20: 650 | C20: =B20/2 -> 325 | D20: BBVA | I20: GBM
A21: Luz | B21: 400 | C21: =B21/2 -> 200 | D21: Nu | F21: Auto | G21: 8000 | H21: =G21/2 -> 4000 | I21: GBM
A22: Internet | B22: 1200 | C22: =B22/2 -> 600 | D22: Nu | F22: Cetes | G22: 8000 | H22: =G22/2 -> 4000 | I22: Cetes
A23: Agua | B23: 200 | C23: =B23/2 -> 100 | D23: BBVA | F23: Supermercado | G23: 14000 | H23: =G23/2 -> 7000
A24: Plan movil Dalia | B24: 499 | C24: =B24/2 -> 249.5 | D24: Nu | F24: Gasolina | G24: 4000 | H24: =G24/2 -> 2000
A25: Plan movil Alfredo | B25: =499+199 -> 698 | C25: =B25/2 -> 349 | D25: Nu
A27: Subtotal | B27: =SUM(B18:B26) -> 3955.3333 | C27: =SUM(C18:C26) -> 1977.6667 | F27: Subtotal | G27: =SUM(G17:G26) -> 66544 | H27: =SUM(H17:H26) -> 33272
A28: Total | B28: =CEILING(SUM(B17:B25), 100) -> 4000 | C28: =CEILING(SUM(C17:C25), 100) -> 2000 | F28: Total | G28: =CEILING(SUM(G17:G25), 100) -> 66600 | H28: =CEILING(SUM(H17:H25), 100) -> 33300 | K28: =H18+H19 -> 9522
K29: =H6+H17+K28 -> 32522
F31: Quincenal | G31: Mensual
D32: =M3 -> Santander | F32: =CEILING(SUMIF($D1:$D26, M3, $C1:$C26) + SUMIF($I1:$I26, M3,$H1:$H26),100) -> 32600 | G32: =CEILING(SUMIF($D1:$D26, M3, $B1:$B26) + SUMIF($I1:$I26, M3,$G1:$G26),100) -> 65100 | K32: =K29-21000 -> 11522
D33: =M4 -> Nu | F33: =CEILING(SUMIF($D1:$D26, M4, $C1:$C26) + SUMIF($I1:$I26, M4,$H1:$H26),100) -> 3600 | G33: =CEILING(SUMIF($D1:$D26, M4, $B1:$B26) + SUMIF($I1:$I26, M4,$G1:$G26),100) -> 7100
D34: =M5 -> GBM | F34: =CEILING(SUMIF($D1:$D26, M5, $C1:$C26) + SUMIF($I1:$I26, M5,$H1:$H26),100) -> 4100 | G34: =CEILING(SUMIF($D1:$D26, M5, $B1:$B26) + SUMIF($I1:$I26, M5,$G1:$G26),100) -> 8100
D35: =M6 -> Finamex | F35: =CEILING(SUMIF($D1:$D26, M6, $C1:$C26) + SUMIF($I1:$I26, M6,$H1:$H26),100) -> 1100 | G35: =CEILING(SUMIF($D1:$D26, M6, $B1:$B26) + SUMIF($I1:$I26, M6,$G1:$G26),100) -> 2100
D36: =M7 -> BBVA | F36: =CEILING(SUMIF($D1:$D26, M7, $C1:$C26) + SUMIF($I1:$I26, M7,$H1:$H26),100) -> 2300 | G36: =CEILING(SUMIF($D1:$D26, M7, $B1:$B26) + SUMIF($I1:$I26, M7,$G1:$G26),100) -> 4500
D37: =M8 -> Cetes | F37: =CEILING(SUMIF($D1:$D26, M8, $C1:$C26) + SUMIF($I1:$I26, M8,$H1:$H26),100) -> 4000 | G37: =CEILING(SUMIF($D1:$D26, M8, $B1:$B26) + SUMIF($I1:$I26, M8,$G1:$G26),100) -> 8000
D38: Efectivo | F38: =CEILING(SUMIF($D1:$D26, M9, $C1:$C26) + SUMIF($I1:$I26, M9,$H1:$H26),100) -> 2700 | G38: =CEILING(SUMIF($D1:$D26, M9, $B1:$B26) + SUMIF($I1:$I26, M9,$G1:$G26),100) -> 5400
F41: =SUM(F32:F38) -> 50400 | G41: =SUM(G32:G38) -> 100300

Sheet From 15.08.23
A1: Subscripciones | B1: Mensual | C1: Quincenal | D1: Budget category | E1: Account | G1: Auto | H1: Mensual | I1: Quincenal | J1: Budget category | K1: Account | M1: Hogar | N1: Mensual | O1: Quincenal | P1: Budget category | Q1: Account | S1: Cuentas | T1: Categorias | U1: Codigo
A2: Prime | B2: =899/12 -> 74.916667 | C2: =B2/2 -> 37.458333 | D2: Want | E2: Stori + | G2: Verificacion | H2: =(600*2)/12 -> 100 | I2: =H2/2 -> 50 | J2: Need | K2: Nu | M2: Luz | N2: 500 | O2: =N2/2 -> 250 | P2: Need | Q2: Nu | S2: Nu | T2: Need | U2: 011
A3: Digital Ocean | B3: =IFERROR(__xludf.DUMMYFUNCTION("GOOGLEFINANCE(""CURRENCY:USDMXN"")*6"),103.30260000000001) -> 103.3026 | C3: =B3/2 -> 51.6513 | D3: Want | E3: Nu | G3: Tenencia | H3: =2500/12 -> 208.33333 | I3: =H3/2 -> 104.16667 | J3: Need | K3: Stori + | M3: Gas | N3: 650 | O3: =N3/2 -> 325 | P3: Need | Q3: HSBC | S3: Santander | T3: Want | U3: 002
A4: Paramount | B4: 109 | C4: =B4/2 -> 54.5 | D4: Want | E4: Nu | G4: Lavado | H4: 600 | I4: =H4/2 -> 300 | J4: Want | K4: Efectivo | M4: Renta | N4: 37500 | O4: =N4/2 -> 18750 | P4: Need | Q4: HSBC Ahorro | S4: GBM | T4: Savings | U4: 021
A5: HBO | B5: =399/3 -> 133 | C5: =B5/2 -> 66.5 | D5: Want | E5: Nu | G5: Seguro | H5: =10000/12 -> 833.33333 | I5: =H5/2 -> 416.66667 | J5: Need | K5: Stori + | S5: Stori + | T5: Debt | U5: 022
A6: NFL game pass | B6: =2500/12 -> 208.33333 | C6: =B6/2 -> 104.16667 | D6: Want | E6: Stori + | G6: Gasolina | H6: 3500 | I6: =H6/2 -> 1750 | J6: Need | K6: HSBC | M6: Subtotal | N6: =SUM(N2:N4) -> 38650 | O6: =SUM(O2:O4) -> 19325 | S6: BBVA | T6: Free | U6: 003
A7: Disney | B7: 249 | C7: =B7/2 -> 124.5 | D7: Want | E7: Nu | G7: Cuota Auto Nuevo / Mtto | H7: 11000 | I7: =H7/2 -> 5500 | J7: Savings | K7: GBM | M7: Total(redondeado) | N7: =CEILING(N6, 100) -> 38700 | O7: =CEILING(O6, 100) -> 19400 | S7: Dalia | U7: 005
A8: Netflix | B8: 299 | C8: =B8/2 -> 149.5 | D8: Want | E8: Nu | S8: HSBC | U8: 001
A9: Frontend masters | B9: =IFERROR(__xludf.DUMMYFUNCTION("GOOGLEFINANCE(""CURRENCY:USDMXN"")*39"),671.4669000000001) -> 671.4669 | C9: =B9/2 -> 335.73345 | D9: Want | E9: Nu | M9: Santa Anita | N9: Mensual | O9: Quincenal | P9: Budget category | Q9: Account | S9: Efectivo
A10: Uber one | B10: 70 | C10: =70/2 -> 35 | D10: Want | E10: Nu | M10: Predial | N10: =600/12 -> 50 | O10: =N10/2 -> 25 | P10: Need | Q10: Stori + | S10: Stori | U10: 013
G11: Subtotal | H11: =SUM(H2:H7) -> 16241.667 | I11: =SUM(I2:I7) -> 8120.8333 | M11: Agua | N11: 200 | O11: =N11/2 -> 100 | P11: Need | Q11: Nu | S11: Rappi | U11: 012
A12: Subtotal | B12: =SUM(B2:B10) -> 1918.0195 | C12: =SUM(C2:C10) -> 959.00975 | G12: Total(redondeado) | H12: =CEILING(H11, 100) -> 16300 | I12: =CEILING(I11, 100) -> 8200 | M12: Mantenimiento | N12: 1800 | O12: =N12/2 -> 900 | P12: Need | Q12: BBVA | S12: HSBC Ahorro | U12: 023
A13: Total (Redondeado) | B13: =CEILING(B12, 100) -> 2000 | C13: =CEILING(C12, 100) -> 1000 | M13: Hipoteca | N13: =6500 -> 6500 | O13: =N13/2 -> 3250 | P13: Debt | Q13: Santander
M14: Renta | P14: Savings | Q14: Santander
M15: Subtotal | N15: =SUM(N10:N14) -> 8550 | O15: =SUM(O10:O14) -> 4275
M16: Total(redondeado) | N16: =CEILING(N15, 100) -> 8600 | O16: =CEILING(O15, 100) -> 4300
A18: Telecomunicaciones | B18: Mensual | C18: Quincenal | D18: Budget category | E18: Account | G18: Variables | H18: Mensual | I18: Quincenal | J18: Budget category | K18: Account | M18: Educacion y Actividades | N18: Mensual | O18: Quincenal | P18: Budget category | Q18: Account
A19: Plan movil Dalia | B19: 499 | C19: =B19/2 -> 249.5 | D19: Want | E19: Nu | G19: Dalia mensualidad | H19: 2000 | I19: =H19/2 -> 1000 | J19: Want | K19: Dalia | M19: Inscripcion Leander | N19: =(7500)/12 -> 625 | O19: =N19/2 -> 312.5 | P19: Debt | Q19: Stori +
A20: Plan movil Alfredo | B20: =499+199 -> 698 | C20: =B20/2 -> 349 | D20: Want | E20: Nu | G20: Limpieza | H20: =500*8 -> 4000 | I20: =H20/2 -> 2000 | J20: Want | K20: Efectivo | M20: Inscripcion Lena | N20: =(7500)/12 -> 625 | O20: =N20/2 -> 312.5 | P20: Debt | Q20: Stori +
A21: Internet | B21: 1169 | C21: =B21/2 -> 584.5 | D21: Need | E21: Nu | G21: Efectivo | H21: 4000 | I21: =H21/2 -> 2000 | J21: Need | K21: Efectivo | M21: Ballet | N21: 1200 | O21: =N21/2 -> 600 | P21: Want | Q21: Dalia
G22: Libre | H22: 7000 | I22: =H22/2 -> 3500 | J22: Want | K22: HSBC | M22: Colegiatura Leander | N22: =7124+1600+600 -> 9324 | O22: =N22/2 -> 4662 | P22: Need | Q22: HSBC Ahorro
G23: Supermercado | H23: 12000 | I23: =H23/2 -> 6000 | J23: Need | K23: HSBC | M23: Colegiatura Lena | N23: =7520+1600+600 -> 9720 | O23: =N23/2 -> 4860 | P23: Need | Q23: HSBC Ahorro
G24: Bicicleta | I24: =H24/2 -> 0 | J24: Savings | K24: Stori +
A26: Subtotal | B26: =SUM(B19:B22) -> 2366 | C26: =SUM(C19:C22) -> 1183 | G26: Subtotal | H26: =SUM(H19:H25) -> 29000 | I26: =SUM(I19:I25) -> 14500 | M26: Subtotal | N26: =SUM(N19:N23) -> 21494 | O26: =SUM(O19:O23) -> 10747
A27: Total(redondeado) | B27: =CEILING(B26, 100) -> 2400 | C27: =CEILING(C26, 100) -> 1200 | G27: Total(redondeado) | H27: =CEILING(H26, 100) -> 29000 | I27: =CEILING(I26, 100) -> 14500 | M27: Total(redondeado) | N27: =CEILING(N26, 100) -> 21500 | O27: =CEILING(O26, 100) -> 10800
A31: Ahorro
A32: Ahorro | B32: 3000 | C32: =B32/2 -> 1500 | D32: Savings | E32: Nu | R32: Programada
A33: CETES | B33: 8000 | C33: =B33/2 -> 4000 | D33: Savings | E33: HSBC | O33: Stori + | P33: =SUMIF($E$2:$E$34, O33, $C$2:$C$34) + SUMIF($K$2:$K$25, O33, $I$2:$I$25) + SUMIF($Q$2:$Q$25, O33, $O$2:$O$25) -> 1312.4583 | Q33: =CEILING(P33, 100) -> 1400 | R33: Si
O34: BBVA | P34: =SUMIF($E$2:$E$34, O34, $C$2:$C$34) + SUMIF($K$2:$K$25, O34, $I$2:$I$25) + SUMIF($Q$2:$Q$25, O34, $O$2:$O$25) -> 900 | Q34: =CEILING(P34, 100) -> 900 | R34: Si
A35: Subtotal | B35: =SUM(B31:B34) -> 11000 | C35: =SUM(C31:C34) -> 5500 | O35: Dalia | P35: =SUMIF($E$2:$E$34, O35, $C$2:$C$34) + SUMIF($K$2:$K$25, O35, $I$2:$I$25) + SUMIF($Q$2:$Q$25, O35, $O$2:$O$25) -> 1600 | Q35: =CEILING(P35, 100) -> 1600 | R35: Si
A36: Total(redondeado) | B36: =CEILING(B35, 100) -> 11000 | C36: =CEILING(C35, 100) -> 5500 | O36: Nu | P36: =SUMIF($E$2:$E$34, O36, $C$2:$C$34) + SUMIF($K$2:$K$25, O36, $I$2:$I$25) + SUMIF($Q$2:$Q$25, O36, $O$2:$O$25) -> 3900.3848 | Q36: =CEILING(P36, 100) -> 4000 | R36: Si
O37: GBM | P37: =SUMIF($E$2:$E$34, O37, $C$2:$C$34) + SUMIF($K$2:$K$25, O37, $I$2:$I$25) + SUMIF($Q$2:$Q$25, O37, $O$2:$O$25) -> 5500 | Q37: =CEILING(P37, 100) -> 5500 | R37: Si
A38: Salario quincenal | B38: =B39/2 -> 66000 | O38: Santander | P38: =SUMIF($E$2:$E$34, O38, $C$2:$C$34) + SUMIF($K$2:$K$25, O38, $I$2:$I$25) + SUMIF($Q$2:$Q$25, O38, $O$2:$O$25) -> 3250 | Q38: =CEILING(P38, 100) -> 3300 | R38: Si
A39: Salario Mensual | B39: 132000 | O39: HSBC | P39: =SUMIF($E$2:$E$34, O39, $C$2:$C$34) + SUMIF($K$2:$K$25, O39, $I$2:$I$25) + SUMIF($Q$2:$Q$25, O39, $O$2:$O$25) -> 15575 | Q39: =CEILING(P39, 100) -> 15600
G40: =SUMIF($D$2:$D$34,T2,$C2:$C$34)+SUMIF($J$2:$J$25,T2,$I2:I$25)+SUMIF($P$2:$P$25,T2,$O$2:$O$25) -> 40777.333 | H40: =CEILING(G40*2, 100) -> 81600 | I40: =CEILING(H40, 100) -> 81600 | J40: =((I40*100)/$B$39)/100 -> 0.61818182 | O40: HSBC Ahorro | P40: =SUMIF($E$2:$E$34, O40, $C$2:$C$34) + SUMIF($K$2:$K$25, O40, $I$2:$I$25) + SUMIF($Q$2:$Q$25, O40, $O$2:$O$25) -> 28272 | Q40: =CEILING(P40, 100) -> 28300 | R40: Si
G41: =SUMIF($D$2:$D$34,T3,$C$2:$C$34)+SUMIF($J$2:$J$25,T3,$I$2:$I$25)+SUMIF($P$2:$P$25,T3,$O$2:$O$25) -> 8957.5097 | H41: =CEILING(G41, 100) -> 9000 | I41: =CEILING(H41*2, 100) -> 18000 | J41: =((I41*100)/$B$39)/100 -> 0.13636364 | O41: Efectivo | P41: =SUMIF($E$2:$E$34, O41, $C$2:$C$34) + SUMIF($K$2:$K$25, O41, $I$2:$I$25) + SUMIF($Q$2:$Q$25, O41, $O$2:$O$25) -> 4300 | Q41: =CEILING(P41, 100) -> 4300
G42: =SUMIF($D$2:$D$34,T4,$C2:$C34)+SUMIF($J$2:$J$25,T4,$I$2:$I$25)+SUMIF($P$2:$P$25,T4,$O$2:$O$25)+SUMIF($D$2:$D$34,T5,$C2:$C34)+SUMIF($J$2:$J$25,T5,$I$2:$I$25)+SUMIF($P$2:$P$25,T5,$O$2:$O$25) -> 14875 | H42: =CEILING(G42, 100) -> 14900 | I42: =CEILING(H42*2, 100) -> 29800 | J42: =((I42*100)/$B$39)/100 -> 0.22575758
G44: =SUM(G40:G42) -> 64609.843 | I44: =M43-SUM(I40:I42) -> -129400 | J44: =SUM(J40:J42) -> 0.98030303 | P44: =SUM(P33:P41) -> 64609.843 | Q44: =SUM(Q33:Q41) -> 64900
M46: =I11+I26+O6+O15+O26+C12+C26+C35 -> 64609.843

Sheet Until 31.07.2024
A1: Kinder | J1: Mensual | K1: Quincenal
A2: Nombre | B2: Mensual | C2: Quincenal | D2: Es Anual | I2: Total | J2: =B13+B28+B36+B43+B55+B70+B78 -> 135420.5 | K2: =C13+C28+C36+C43+C55+C78+C70 -> 67710.25
A3: Colegiatura Lena | B3: 7915 | C3: =B3/2 -> 3957.5 | D3: FALSE | E3: HSBC Ahorro
A4: Colegiatura Leander | B4: 7915 | C4: =B4/2 -> 3957.5 | D4: FALSE | E4: HSBC Ahorro
A5: Horario Extendido Lena | B5: 2200 | C5: =B5/2 -> 1100 | D5: FALSE | E5: HSBC Ahorro
A6: Horario Extendido Leander | B6: 2200 | C6: =B6/2 -> 1100 | D6: FALSE | E6: HSBC Ahorro
A7: Ballet | B7: 1200 | C7: =B7/2 -> 600 | D7: FALSE | E7: Nu Dalia
A8: Natacion Lena | B8: 1180 | C8: =B8/2 -> 590 | D8: FALSE | E8: Nu Gastos
A9: Natacion Leander | B9: 1095 | C9: =B9/2 -> 547.5 | D9: FALSE | E9: Nu Gastos
A10: Inscripcion Lena | B10: =CEILING((9500)/12, 100) -> 800 | C10: =B10/2 -> 400 | D10: TRUE | E10: Nu Anual
A11: Inscripcion Leander | B11: =CEILING((7500)/12, 100) -> 700 | C11: =B11/2 -> 350 | D11: TRUE | E11: Nu Anual
I12: Total Mensual | J12: Total quincenal | K12: Programada
A13: Total | B13: =SUM(B2:B12) -> 25205 | C13: =SUM(C2:C12) -> 12602.5 | H13: BBVA | I13: =CEILING(SUMIF($E$2:$E$81, H13, $B$2:$B$81),100) -> 1800 | J13: =CEILING(SUMIF($E$2:$E$81, H13, $C$2:$C$81),100) -> 900 | K13: Si
H14: Cetes | I14: =CEILING(SUMIF($E$2:$E$81, H14, $B$2:$B$81),100) -> 8000 | J14: =CEILING(SUMIF($E$2:$E$81, H14, $C$2:$C$81),100) -> 4000 | K14: Si (Portal Cetes)
A15: Suscripciones | H15: GBM | I15: =CEILING(SUMIF($E$2:$E$81, H15, $B$2:$B$81),100) -> 2000 | J15: =CEILING(SUMIF($E$2:$E$81, H15, $C$2:$C$81),100) -> 1000 | K15: Si
A16: Nombre | B16: Mensual | C16: Quincenal | H16: HSBC | I16: =CEILING(SUMIF($E$2:$E$81, H16, $B$2:$B$81),100) -> 28800 | J16: =CEILING(SUMIF($E$2:$E$81, H16, $C$2:$C$81),100) -> 14400
A17: Frontend masters | B17: =IFERROR(__xludf.DUMMYFUNCTION("CEILING(GOOGLEFINANCE(""CURRENCY:USDMXN"")*39, 10)"),680.0) -> 680 | C17: =B17/2 -> 340 | D17: FALSE | E17: Stori + | H17: HSBC Ahorro | I17: =CEILING(SUMIF($E$2:$E$81, H17, $B$2:$B$81),100) -> 57800 | J17: =CEILING(SUMIF($E$2:$E$81, H17, $C$2:$C$81),100) -> 28900 | K17: Si
A18: Netflix | B18: =CEILING(299+69,10) -> 370 | C18: =B18/2 -> 185 | D18: FALSE | E18: Stori + | H18: Nu Gastos | I18: =CEILING(SUMIF($E$2:$E$81, H18, $B$2:$B$81),100) -> 5900 | J18: =CEILING(SUMIF($E$2:$E$81, H18, $C$2:$C$81),100) -> 3000 | K18: Si
A19: Disney | B19: =CEILING(249,10) -> 250 | C19: =B19/2 -> 125 | D19: FALSE | E19: Stori + | H19: Nu Anual | I19: =CEILING(SUMIF($E$2:$E$81, H19, $B$2:$B$81),100) -> 1800 | J19: =CEILING(SUMIF($E$2:$E$81, H19, $C$2:$C$81),100) -> 900 | K19: Si
A20: NFL game pass | B20: =CEILING(2500/12, 10) -> 210 | C20: =B20/2 -> 105 | D20: TRUE | E20: Nu Anual | H20: Nu Auto | I20: =CEILING(SUMIF($E$2:$E$81, H20, $B$2:$B$81),100) -> 15400 | J20: =CEILING(SUMIF($E$2:$E$81, H20, $C$2:$C$81),100) -> 7700 | K20: Si
A21: Spotify | B21: 200 | C21: =B21/2 -> 100 | D21: FALSE | E21: Stori + | H21: Nu Dalia | I21: =CEILING(SUMIF($E$2:$E$81, H21, $B$2:$B$81),100) -> 3200 | J21: =CEILING(SUMIF($E$2:$E$81, H21, $C$2:$C$81),100) -> 1600 | K21: SI
A22: HBO | B22: =CEILING(199,10) -> 200 | C22: =B22/2 -> 100 | D22: FALSE | E22: Stori + | H22: Santander | I22: =CEILING(SUMIF($E$2:$E$81, H22, $B$2:$B$81),100) -> 5200 | J22: =CEILING(SUMIF($E$2:$E$81, H22, $C$2:$C$81),100) -> 2600 | K22: Si
A23: Paramount | B23: =CEILING(109,10) -> 110 | C23: =B23/2 -> 55 | D23: FALSE | E23: Stori + | H23: Stori + | I23: =CEILING(SUMIF($E$2:$E$81, H23, $B$2:$B$81),100) -> 5700 | J23: =CEILING(SUMIF($E$2:$E$81, H23, $C$2:$C$81),100) -> 2900 | K23: Si
A24: Digital Ocean | B24: =IFERROR(__xludf.DUMMYFUNCTION("CEILING(GOOGLEFINANCE(""CURRENCY:USDMXN"")*6, 10)"),110.0) -> 110 | C24: =B24/2 -> 55 | D24: FALSE | E24: Stori +
A25: Prime | B25: =CEILING(899/12, 10) -> 80 | C25: =B25/2 -> 40 | D25: TRUE | E25: Nu Anual | J25: =SUM(J13:J23) -> 67900
A26: Uber one | B26: 70 | C26: =B26/2 -> 35 | D26: FALSE | E26: Stori +
A28: Total | B28: =SUM(B17:B27) -> 2280 | C28: =SUM(C17:C27) -> 1140 | H28: Nu total | J28: =J18+J19+J20 -> 11600
A30: Telecomunicaciones
A31: Nombre | B31: Mensual | C31: Quincenal
A32: Totalplay (Internet + TV) | B32: 1200 | C32: =B32/2 -> 600 | D32: FALSE | E32: Stori +
A33: Movistar Dalia | B33: 500 | C33: =B33/2 -> 250 | D33: FALSE | E33: Stori +
A34: Movistar Alfredo | B34: 450 | C34: =B34/2 -> 225 | D34: FALSE | E34: Stori +
A36: Total | B36: =SUM(B32:B35) -> 2150 | C36: =SUM(C32:C35) -> 1075 | J36: =J18+J19+J20 -> 11600
A38: Ahorro
A39: Nombre | B39: Mensual | C39: Quincenal
A40: Largo plazo | B40: 8000 | C40: =B40/2 -> 4000 | D40: FALSE | E40: Cetes
A41: Personal | B41: 2000 | C41: =B41/2 -> 1000 | D41: FALSE | E41: GBM
A43: Total | B43: =SUM(B40:B42) -> 10000 | C43: =SUM(C40:C42) -> 5000
A45: Auto | J45: =IFERROR(__xludf.DUMMYFUNCTION("SUM(FILTER(J12:J23,J12:J23<>J12))"),67900.0) -> 67900
A46: Nombre | B46: Mensual | C46: Quincenal
A47: Nuevo Auto | B47: 10000 | C47: =B47/2 -> 5000 | D47: FALSE | E47: Nu Auto
A48: Gasolina | B48: 3000 | C48: =B48/2 -> 1500 | D48: FALSE | E48: Nu Auto
A49: Seguro | B49: =CEILING(10000/12, 100) -> 900 | C49: =B49/2 -> 450 | D49: TRUE | E49: Nu Auto
A50: Matenimiento | B50: 750 | C50: =B50/2 -> 375 | D50: FALSE | E50: Nu Auto
A51: Lavado | B51: 400 | C51: =B51/2 -> 200 | D51: FALSE | E51: Nu Auto
A52: Tenencia | B52: =CEILING(2500/12, 10) -> 210 | C52: =B52/2 -> 105 | D52: TRUE | E52: Nu Auto
A53: Verificacion | B53: =CEILING((700*2)/12, 10) -> 120 | C53: =B53/2 -> 60 | D53: FALSE | E53: Nu Auto
A55: Total | B55: =SUM(B47:B54) -> 15380 | C55: =SUM(C47:C54) -> 7690
A57: Zuhause
A58: Nombre | B58: Mensual | C58: Quincenal
A59: Renta | B59: 37500 | C59: =B59/2 -> 18750 | D59: FALSE | E59: HSBC Ahorro
A60: Supermercado | B60: 13500 | C60: =B60/2 -> 6750 | D60: FALSE | E60: HSBC
A61: Limpieza | B61: =400*12 -> 4800 | C61: =B61/2 -> 2400 | D61: FALSE | E61: HSBC
A62: Electricidad | B62: 650 | C62: =B62/2 -> 325 | D62: FALSE | E62: Stori +
A63: Gas | B63: 500 | C63: =B63/2 -> 250 | D63: FALSE | E63: Stori +
A64: Agua | B64: =(600+111)/2 -> 355.5 | C64: =B64/2 -> 177.75 | D64: FALSE | E64: Stori +
A65: Sta Anita
A66: Hipoteca | B66: 5000 | C66: =B66/2 -> 2500 | D66: FALSE | E66: Santander
A67: Mantenimiento | B67: 1800 | C67: =B67/2 -> 900 | D67: FALSE | E67: BBVA
A68: Predial | B68: 200 | C68: =B68/2 -> 100 | D68: TRUE | E68: Santander
A70: Total | B70: =SUM(B59:B69) -> 64305.5 | C70: =SUM(C59:C69) -> 32152.75
A72: Miscelaneos
A73: Sports World | B73: 3600 | C73: =B73/2 -> 1800 | D73: FALSE | E73: Nu Gastos
A74: Libre | B74: 6500 | C74: =B74/2 -> 3250 | D74: FALSE | E74: HSBC
A75: Efectivo | B75: 4000 | C75: =B75/2 -> 2000 | D75: FALSE | E75: HSBC
A76: Dalia mensualidad | B76: 2000 | C76: =B76/2 -> 1000 | D76: FALSE | E76: Nu Dalia
A78: Total | B78: =SUM(B73:B76) -> 16100 | C78: =SUM(C73:C76) -> 8050
